Workbook

Sheet Resumo
C3: Resumo analítico
C5: Valores derivados por fórmulas; indicadores de Brasil municipal e Bélgica permanecem em níveis institucionais distintos.
C6: Consulte unidade por linha. R$ correntes e R$ médios de 2024 não são intercambiáveis.
C8: Indicador | D8: Unidade | E8: Arcoverde/PE | F8: Araripina/PE | G8: Bélgica
C9: Receita bruta reportada — 2024 | D9: R$ correntes | E9: =SUMIFS('Cálculos Municipais'!$E$9:$E$28,'Cálculos Municipais'!$C$9:$C$28,"Arcoverde/PE",'Cálculos Municipais'!$D$9:$D$28,2024) -> 3.3882565e+08 | F9: =SUMIFS('Cálculos Municipais'!$E$9:$E$28,'Cálculos Municipais'!$C$9:$C$28,"Araripina/PE",'Cálculos Municipais'!$D$9:$D$28,2024) -> 4.0675034e+08 | G9: —
C10: Despesa empenhada total — 2024 | D10: R$ correntes | E10: =SUMIFS('Cálculos Municipais'!$I$9:$I$28,'Cálculos Municipais'!$C$9:$C$28,"Arcoverde/PE",'Cálculos Municipais'!$D$9:$D$28,2024) -> 3.1725955e+08 | F10: =SUMIFS('Cálculos Municipais'!$I$9:$I$28,'Cálculos Municipais'!$C$9:$C$28,"Araripina/PE",'Cálculos Municipais'!$D$9:$D$28,2024) -> 3.9993486e+08 | G10: —
C11: Receita bruta real — 2024 | D11: R$ médios de 2024 | E11: =SUMIFS('Cálculos Municipais'!$U$9:$U$28,'Cálculos Municipais'!$C$9:$C$28,"Arcoverde/PE",'Cálculos Municipais'!$D$9:$D$28,2024) -> 3.3882565e+08 | F11: =SUMIFS('Cálculos Municipais'!$U$9:$U$28,'Cálculos Municipais'!$C$9:$C$28,"Araripina/PE",'Cálculos Municipais'!$D$9:$D$28,2024) -> 4.0675034e+08 | G11: —
C12: Despesa empenhada real — 2024 | D12: R$ médios de 2024 | E12: =SUMIFS('Cálculos Municipais'!$V$9:$V$28,'Cálculos Municipais'!$C$9:$C$28,"Arcoverde/PE",'Cálculos Municipais'!$D$9:$D$28,2024) -> 3.1725955e+08 | F12: =SUMIFS('Cálculos Municipais'!$V$9:$V$28,'Cálculos Municipais'!$C$9:$C$28,"Araripina/PE",'Cálculos Municipais'!$D$9:$D$28,2024) -> 3.9993486e+08 | G12: —
C13: Crescimento real da receita, 2015–2024 | D13: % acumulado | E13: =IFERROR(SUMIFS('Cálculos Municipais'!$U$9:$U$28,'Cálculos Municipais'!$C$9:$C$28,"Arcoverde/PE",'Cálculos Municipais'!$D$9:$D$28,2024)/SUMIFS('Cálculos Municipais'!$U$9:$U$28,'Cálculos Municipais'!$C$9:$C$28,"Arcoverde/PE",'Cálculos Municipais'!$D$9:$D$28,2015)-1,"") -> 0.61255719 | F13: =IFERROR(SUMIFS('Cálculos Municipais'!$U$9:$U$28,'Cálculos Municipais'!$C$9:$C$28,"Araripina/PE",'Cálculos Municipais'!$D$9:$D$28,2024)/SUMIFS('Cálculos Municipais'!$U$9:$U$28,'Cálculos Municipais'!$C$9:$C$28,"Araripina/PE",'Cálculos Municipais'!$D$9:$D$28,2015)-1,"") -> 0.68691709 | G13: não aplicável
C14: Crescimento real da despesa empenhada, 2015–2024 | D14: % acumulado | E14: =IFERROR(SUMIFS('Cálculos Municipais'!$V$9:$V$28,'Cálculos Municipais'!$C$9:$C$28,"Arcoverde/PE",'Cálculos Municipais'!$D$9:$D$28,2024)/SUMIFS('Cálculos Municipais'!$V$9:$V$28,'Cálculos Municipais'!$C$9:$C$28,"Arcoverde/PE",'Cálculos Municipais'!$D$9:$D$28,2015)-1,"") -> 0.56129017 | F14: =IFERROR(SUMIFS('Cálculos Municipais'!$V$9:$V$28,'Cálculos Municipais'!$C$9:$C$28,"Araripina/PE",'Cálculos Municipais'!$D$9:$D$28,2024)/SUMIFS('Cálculos Municipais'!$V$9:$V$28,'Cálculos Municipais'!$C$9:$C$28,"Araripina/PE",'Cálculos Municipais'!$D$9:$D$28,2015)-1,"") -> 0.76038013 | G14: não aplicável
C15: Receita tributária / receita bruta — 2024 | D15: % | E15: =SUMIFS('Cálculos Municipais'!$Y$9:$Y$28,'Cálculos Municipais'!$C$9:$C$28,"Arcoverde/PE",'Cálculos Municipais'!$D$9:$D$28,2024) -> 0.10290056 | F15: =SUMIFS('Cálculos Municipais'!$Y$9:$Y$28,'Cálculos Municipais'!$C$9:$C$28,"Araripina/PE",'Cálculos Municipais'!$D$9:$D$28,2024) -> 0.064188236 | G15: —
C16: Transferências correntes / receita bruta — 2024 | D16: % | E16: =SUMIFS('Cálculos Municipais'!$Z$9:$Z$28,'Cálculos Municipais'!$C$9:$C$28,"Arcoverde/PE",'Cálculos Municipais'!$D$9:$D$28,2024) -> 0.7500492 | F16: =SUMIFS('Cálculos Municipais'!$Z$9:$Z$28,'Cálculos Municipais'!$C$9:$C$28,"Araripina/PE",'Cálculos Municipais'!$D$9:$D$28,2024) -> 0.73462152 | G16: —
C17: Receita bruta real per capita — 2024 | D17: R$ 2024/habitante | E17: =SUMIFS('Cálculos Municipais'!$W$9:$W$28,'Cálculos Municipais'!$C$9:$C$28,"Arcoverde/PE",'Cálculos Municipais'!$D$9:$D$28,2024) -> 4131.8689 | F17: =SUMIFS('Cálculos Municipais'!$W$9:$W$28,'Cálculos Municipais'!$C$9:$C$28,"Araripina/PE",'Cálculos Municipais'!$D$9:$D$28,2024) -> 4514.2318 | G17: —
C18: Despesa empenhada real per capita — 2024 | D18: R$ 2024/habitante | E18: =SUMIFS('Cálculos Municipais'!$X$9:$X$28,'Cálculos Municipais'!$C$9:$C$28,"Arcoverde/PE",'Cálculos Municipais'!$D$9:$D$28,2024) -> 3868.8774 | F18: =SUMIFS('Cálculos Municipais'!$X$9:$X$28,'Cálculos Municipais'!$C$9:$C$28,"Araripina/PE",'Cálculos Municipais'!$D$9:$D$28,2024) -> 4438.5917 | G18: —
C19: População — 2024 | D19: pessoas | E19: =SUMIFS('Cálculos Municipais'!$Q$9:$Q$28,'Cálculos Municipais'!$C$9:$C$28,"Arcoverde/PE",'Cálculos Municipais'!$D$9:$D$28,2024) -> 82003 | F19: =SUMIFS('Cálculos Municipais'!$Q$9:$Q$28,'Cálculos Municipais'!$C$9:$C$28,"Araripina/PE",'Cálculos Municipais'!$D$9:$D$28,2024) -> 90104 | G19: —
C20: PIB municipal — 2023 | D20: R$ correntes | E20: =SUMIFS('Cálculos Municipais'!$R$9:$R$28,'Cálculos Municipais'!$C$9:$C$28,"Arcoverde/PE",'Cálculos Municipais'!$D$9:$D$28,2023) -> 1503621000 | F20: =SUMIFS('Cálculos Municipais'!$R$9:$R$28,'Cálculos Municipais'!$C$9:$C$28,"Araripina/PE",'Cálculos Municipais'!$D$9:$D$28,2023) -> 1777713000 | G20: —
C21: Saldo de financiamento líquido — 2025 | D21: % do PIB | G21: =Bélgica!D19 -> -5.2
C22: Dívida bruta consolidada — 2025 | D22: % do PIB | G22: =Bélgica!E19 -> 108.1
C24: Nota: não se calcula superávit/déficit municipal a partir de receita bruta e despesa empenhada sem harmonização completa das deduções; PIB municipal termina em 2023 e população anual falta em 2023.

Sheet Dados DCA
C3: Dados-fonte — Siconfi DCA
C5: Linhas selecionadas para construir os indicadores municipais; não some indicadores distintos.
C6: R$ correntes; manter separadas receitas brutas, deduções e estágios da despesa.
C8: Município | D8: Código IBGE | E8: Ano | F8: Indicador | G8: Arquivo de origem | H8: Anexo | I8: Código da conta | J8: Conta | K8: Coluna contábil | L8: Valor (R$ correntes) | M8: Rótulo do quadro
C9: Arcoverde/PE | D9: 2601201 | E9: 2015 | F9: receita_total_bruta | G9: siconfi_dca_arcoverde_2015.json | H9: DCA-Anexo I-C | I9: TotalReceitas | J9: Total Receitas | K9: Receitas Brutas Realizadas | L9: 1.302675e+08
C10: Arcoverde/PE | D10: 2601201 | E10: 2015 | F10: deducao_fundeb | G10: siconfi_dca_arcoverde_2015.json | H10: DCA-Anexo I-C | I10: TotalReceitas | J10: Total Receitas | K10: Deduções - FUNDEB | L10: -10228661
C11: Arcoverde/PE | D11: 2601201 | E11: 2015 | F11: despesa_empenhada_total | G11: siconfi_dca_arcoverde_2015.json | H11: DCA-Anexo I-D | I11: TotalDespesas | J11: Total Geral da Despesa | K11: Despesas Empenhadas | L11: 1.2598128e+08
C12: Arcoverde/PE | D12: 2601201 | E12: 2015 | F12: despesa_liquidada_total | G12: siconfi_dca_arcoverde_2015.json | H12: DCA-Anexo I-D | I12: TotalDespesas | J12: Total Geral da Despesa | K12: Despesas Liquidadas | L12: 1.2598128e+08
C13: Arcoverde/PE | D13: 2601201 | E13: 2015 | F13: despesa_paga_total | G13: siconfi_dca_arcoverde_2015.json | H13: DCA-Anexo I-D | I13: TotalDespesas | J13: Total Geral da Despesa | K13: Despesas Pagas | L13: 1.2028544e+08
C14: Arcoverde/PE | D14: 2601201 | E14: 2015 | F14: receita_tributaria_propria_bruta | G14: siconfi_dca_arcoverde_2015.json | H14: DCA-Anexo I-C | I14: RO1.1.0.0.00.00.00 | J14: 1.1.0.0.00.00.00 - Receita Tributária | K14: Receitas Brutas Realizadas | L14: 11525466
C15: Arcoverde/PE | D15: 2601201 | E15: 2015 | F15: transferencias_correntes_total_brutas | G15: siconfi_dca_arcoverde_2015.json | H15: DCA-Anexo I-C | I15: RO1.7.0.0.00.00.00 | J15: 1.7.0.0.00.00.00 - Transferências Correntes | K15: Receitas Brutas Realizadas | L15: 95184422
C16: Arcoverde/PE | D16: 2601201 | E16: 2015 | F16: transferencias_capital_total_brutas | G16: siconfi_dca_arcoverde_2015.json | H16: DCA-Anexo I-C | I16: RO2.4.0.0.00.00.00 | J16: 2.4.0.0.00.00.00 - Transferências de Capital | K16: Receitas Brutas Realizadas | L16: 4541687.9
C17: Arcoverde/PE | D17: 2601201 | E17: 2015 | F17: transferencias_intergov_correntes_proxy | G17: siconfi_dca_arcoverde_2015.json | H17: DCA-Anexo I-C | I17: RO1.7.2.0.00.00.00 | J17: 1.7.2.0.00.00.00 - Transferências Intergovernamentais | K17: Receitas Brutas Realizadas | L17: 91796680
C18: Arcoverde/PE | D18: 2601201 | E18: 2015 | F18: transferencias_intergov_capital_proxy | G18: siconfi_dca_arcoverde_2015.json | H18: DCA-Anexo I-C | I18: RO2.4.2.0.00.00.00 | J18: 2.4.2.0.00.00.00 - Transferências Intergovernamentais | K18: Receitas Brutas Realizadas | L18: 1600291.2
C19: Arcoverde/PE | D19: 2601201 | E19: 2016 | F19: receita_total_bruta | G19: siconfi_dca_arcoverde_2016.json | H19: DCA-Anexo I-C | I19: TotalReceitas | J19: Total Receitas | K19: Receitas Brutas Realizadas | L19: 1.4621232e+08
C20: Arcoverde/PE | D20: 2601201 | E20: 2016 | F20: deducao_fundeb | G20: siconfi_dca_arcoverde_2016.json | H20: DCA-Anexo I-C | I20: TotalReceitas | J20: Total Receitas | K20: Deduções - FUNDEB | L20: 11514533
... C28: Arcoverde/PE | D28: 2601201 | E28: 2016 | F28: transferencias_intergov_capital_proxy | G28: siconfi_dca_arcoverde_2016.json | H28: DCA-Anexo I-C | I28: RO2.4.2.0.00.00.00 | J28: 2.4.2.0.00.00.00 - Transferências Intergovernamentais | K28: Receitas Brutas Realizadas | L28: 4328097.7
C29: Arcoverde/PE | D29: 2601201 | E29: 2017 | F29: receita_total_bruta | G29: siconfi_dca_arcoverde_2017.json | H29: DCA-Anexo I-C | I29: TotalReceitas | J29: Total Receitas | K29: Receitas Brutas Realizadas | L29: 1.4729836e+08 | M29: Padrão
C30: Arcoverde/PE | D30: 2601201 | E30: 2017 | F30: deducao_fundeb | G30: siconfi_dca_arcoverde_2017.json | H30: DCA-Anexo I-C | I30: TotalReceitas | J30: Total Receitas | K30: Deduções - FUNDEB | L30: 11283259 | M30: Padrão
C31: Arcoverde/PE | D31: 2601201 | E31: 2017 | F31: despesa_empenhada_total | G31: siconfi_dca_arcoverde_2017.json | H31: DCA-Anexo I-D | I31: TotalDespesas | J31: Total Geral da Despesa | K31: Despesas Empenhadas | L31: 1.4007055e+08 | M31: Padrão
C32: Arcoverde/PE | D32: 2601201 | E32: 2017 | F32: despesa_liquidada_total | G32: siconfi_dca_arcoverde_2017.json | H32: DCA-Anexo I-D | I32: TotalDespesas | J32: Total Geral da Despesa | K32: Despesas Liquidadas | L32: 1.4007055e+08 | M32: Padrão
C33: Arcoverde/PE | D33: 2601201 | E33: 2017 | F33: despesa_paga_total | G33: siconfi_dca_arcoverde_2017.json | H33: DCA-Anexo I-D | I33: TotalDespesas | J33: Total Geral da Despesa | K33: Despesas Pagas | L33: 1.2866128e+08 | M33: Padrão
C34: Arcoverde/PE | D34: 2601201 | E34: 2017 | F34: despesa_empenhada_exceto_intra | G34: siconfi_dca_arcoverde_2017.json | H34: DCA-Anexo I-E | I34: TotalDespesas | J34: Despesas Exceto Intraorçamentárias | K34: Despesas Empenhadas | L34: 1.3350634e+08 | M34: Total Geral da Despesa por Função
C35: Arcoverde/PE | D35: 2601201 | E35: 2017 | F35: despesa_liquidada_exceto_intra | G35: siconfi_dca_arcoverde_2017.json | H35: DCA-Anexo I-E | I35: TotalDespesas | J35: Despesas Exceto Intraorçamentárias | K35: Despesas Liquidadas | L35: 1.3350634e+08 | M35: Total Geral da Despesa por Função
C36: Arcoverde/PE | D36: 2601201 | E36: 2017 | F36: despesa_paga_exceto_intra | G36: siconfi_dca_arcoverde_2017.json | H36: DCA-Anexo I-E | I36: TotalDespesas | J36: Despesas Exceto Intraorçamentárias | K36: Despesas Pagas | L36: 1.2270912e+08 | M36: Total Geral da Despesa por Função
C37: Arcoverde/PE | D37: 2601201 | E37: 2017 | F37: receita_tributaria_propria_bruta | G37: siconfi_dca_arcoverde_2017.json | H37: DCA-Anexo I-C | I37: RO1.1.0.0.00.00.00 | J37: 1.1.0.0.00.00.00 - Receita Tributária | K37: Receitas Brutas Realizadas | L37: 11763761 | M37: Padrão
C38: Arcoverde/PE | D38: 2601201 | E38: 2017 | F38: transferencias_correntes_total_brutas | G38: siconfi_dca_arcoverde_2017.json | H38: DCA-Anexo I-C | I38: RO1.7.0.0.00.00.00 | J38: 1.7.0.0.00.00.00 - Transferências Correntes | K38: Receitas Brutas Realizadas | L38: 1.0632472e+08 | M38: Padrão
C39: Arcoverde/PE | D39: 2601201 | E39: 2017 | F39: transferencias_capital_total_brutas | G39: siconfi_dca_arcoverde_2017.json | H39: DCA-Anexo I-C | I39: RO2.4.0.0.00.00.00 | J39: 2.4.0.0.00.00.00 - Transferências de Capital | K39: Receitas Brutas Realizadas | L39: 5468408.7 | M39: Padrão
C40: Arcoverde/PE | D40: 2601201 | E40: 2017 | F40: transferencias_intergov_correntes_proxy | G40: siconfi_dca_arcoverde_2017.json | H40: DCA-Anexo I-C | I40: RO1.7.2.0.00.00.00 | J40: 1.7.2.0.00.00.00 - Transferências Intergovernamentais | K40: Receitas Brutas Realizadas | L40: 1.0475739e+08 | M40: Padrão
... C279: Arcoverde/PE | D279: 2601201 | E279: 2024 | F279: despesa_funcao_28 | G279: siconfi_dca_arcoverde_2024.json | H279: DCA-Anexo I-E | I279: TotalDespesas | J279: 28 - Encargos Especiais | K279: Despesas Empenhadas | L279: 7811881.9 | M279: Total Geral da Despesa por Função
C280: Araripina/PE | D280: 2601102 | E280: 2015 | F280: receita_total_bruta | G280: siconfi_dca_araripina_2015.json | H280: DCA-Anexo I-C | I280: TotalReceitas | J280: Total Receitas | K280: Receitas Brutas Realizadas | L280: 149488959
C281: Araripina/PE | D281: 2601102 | E281: 2015 | F281: deducao_fundeb | G281: siconfi_dca_araripina_2015.json | H281: DCA-Anexo I-C | I281: TotalReceitas | J281: Total Receitas | K281: Deduções - FUNDEB | L281: -10093010
C282: Araripina/PE | D282: 2601102 | E282: 2015 | F282: despesa_empenhada_total | G282: siconfi_dca_araripina_2015.json | H282: DCA-Anexo I-D | I282: TotalDespesas | J282: Total Geral da Despesa | K282: Despesas Empenhadas | L282: 1.4085029e+08
C283: Araripina/PE | D283: 2601102 | E283: 2015 | F283: despesa_liquidada_total | G283: siconfi_dca_araripina_2015.json | H283: DCA-Anexo I-D | I283: TotalDespesas | J283: Total Geral da Despesa | K283: Despesas Liquidadas | L283: 1.4066153e+08
C284: Araripina/PE | D284: 2601102 | E284: 2015 | F284: despesa_paga_total | G284: siconfi_dca_araripina_2015.json | H284: DCA-Anexo I-D | I284: TotalDespesas | J284: Total Geral da Despesa | K284: Despesas Pagas | L284: 1.3558279e+08
C285: Araripina/PE | D285: 2601102 | E285: 2015 | F285: receita_tributaria_propria_bruta | G285: siconfi_dca_araripina_2015.json | H285: DCA-Anexo I-C | I285: RO1.1.0.0.00.00.00 | J285: 1.1.0.0.00.00.00 - Receita Tributária | K285: Receitas Brutas Realizadas | L285: 6953850.5
C286: Araripina/PE | D286: 2601102 | E286: 2015 | F286: transferencias_correntes_total_brutas | G286: siconfi_dca_araripina_2015.json | H286: DCA-Anexo I-C | I286: RO1.7.0.0.00.00.00 | J286: 1.7.0.0.00.00.00 - Transferências Correntes | K286: Receitas Brutas Realizadas | L286: 1.1927996e+08
C287: Araripina/PE | D287: 2601102 | E287: 2015 | F287: transferencias_capital_total_brutas | G287: siconfi_dca_araripina_2015.json | H287: DCA-Anexo I-C | I287: RO2.4.0.0.00.00.00 | J287: 2.4.0.0.00.00.00 - Transferências de Capital | K287: Receitas Brutas Realizadas | L287: 5963677.5
C288: Araripina/PE | D288: 2601102 | E288: 2015 | F288: transferencias_intergov_correntes_proxy | G288: siconfi_dca_araripina_2015.json | H288: DCA-Anexo I-C | I288: RO1.7.2.0.00.00.00 | J288: 1.7.2.0.00.00.00 - Transferências Intergovernamentais | K288: Receitas Brutas Realizadas | L288: 1.1920818e+08
C289: Araripina/PE | D289: 2601102 | E289: 2015 | F289: transferencias_intergov_capital_proxy | G289: siconfi_dca_araripina_2015.json | H289: DCA-Anexo I-C | I289: RO2.4.2.0.00.00.00 | J289: 2.4.2.0.00.00.00 - Transferências Intergovernamentais | K289: Receitas Brutas Realizadas | L289: 764655.87
C290: Araripina/PE | D290: 2601102 | E290: 2016 | F290: receita_total_bruta | G290: siconfi_dca_araripina_2016.json | H290: DCA-Anexo I-C | I290: TotalReceitas | J290: Total Receitas | K290: Receitas Brutas Realizadas | L290: 1.5301057e+08
C291: Araripina/PE | D291: 2601102 | E291: 2016 | F291: deducao_fundeb | G291: siconfi_dca_araripina_2016.json | H291: DCA-Anexo I-C | I291: TotalReceitas | J291: Total Receitas | K291: Deduções - FUNDEB | L291: 11321945
... C298: Araripina/PE | D298: 2601102 | E298: 2016 | F298: transferencias_intergov_correntes_proxy | G298: siconfi_dca_araripina_2016.json | H298: DCA-Anexo I-C | I298: RO1.7.2.0.00.00.00 | J298: 1.7.2.0.00.00.00 - Transferências Intergovernamentais | K298: Receitas Brutas Realizadas | L298: 1.2208481e+08
C299: Araripina/PE | D299: 2601102 | E299: 2017 | F299: receita_total_bruta | G299: siconfi_dca_araripina_2017.json | H299: DCA-Anexo I-C | I299: TotalReceitas | J299: Total Receitas | K299: Receitas Brutas Realizadas | L299: 1.6198893e+08 | M299: Padrão
C300: Araripina/PE | D300: 2601102 | E300: 2017 | F300: deducao_fundeb | G300: siconfi_dca_araripina_2017.json | H300: DCA-Anexo I-C | I300: TotalReceitas | J300: Total Receitas | K300: Deduções - FUNDEB | L300: 11013976 | M300: Padrão
C301: Araripina/PE | D301: 2601102 | E301: 2017 | F301: despesa_empenhada_total | G301: siconfi_dca_araripina_2017.json | H301: DCA-Anexo I-D | I301: TotalDespesas | J301: Total Geral da Despesa | K301: Despesas Empenhadas | L301: 1.5489164e+08 | M301: Padrão
C302: Araripina/PE | D302: 2601102 | E302: 2017 | F302: despesa_liquidada_total | G302: siconfi_dca_araripina_2017.json | H302: DCA-Anexo I-D | I302: TotalDespesas | J302: Total Geral da Despesa | K302: Despesas Liquidadas | L302: 1.5482652e+08 | M302: Padrão
C303: Araripina/PE | D303: 2601102 | E303: 2017 | F303: despesa_paga_total | G303: siconfi_dca_araripina_2017.json | H303: DCA-Anexo I-D | I303: TotalDespesas | J303: Total Geral da Despesa | K303: Despesas Pagas | L303: 1.4796548e+08 | M303: Padrão
C304: Araripina/PE | D304: 2601102 | E304: 2017 | F304: despesa_empenhada_exceto_intra | G304: siconfi_dca_araripina_2017.json | H304: DCA-Anexo I-E | I304: TotalDespesas | J304: Despesas Exceto Intraorçamentárias | K304: Despesas Empenhadas | L304: 1.4654953e+08 | M304: Total Geral da Despesa por Função
C305: Araripina/PE | D305: 2601102 | E305: 2017 | F305: despesa_liquidada_exceto_intra | G305: siconfi_dca_araripina_2017.json | H305: DCA-Anexo I-E | I305: TotalDespesas | J305: Despesas Exceto Intraorçamentárias | K305: Despesas Liquidadas | L305: 1.4648441e+08 | M305: Total Geral da Despesa por Função
C306: Araripina/PE | D306: 2601102 | E306: 2017 | F306: despesa_paga_exceto_intra | G306: siconfi_dca_araripina_2017.json | H306: DCA-Anexo I-E | I306: TotalDespesas | J306: Despesas Exceto Intraorçamentárias | K306: Despesas Pagas | L306: 1.4083205e+08 | M306: Total Geral da Despesa por Função
C307: Araripina/PE | D307: 2601102 | E307: 2017 | F307: receita_tributaria_propria_bruta | G307: siconfi_dca_araripina_2017.json | H307: DCA-Anexo I-C | I307: RO1.1.0.0.00.00.00 | J307: 1.1.0.0.00.00.00 - Receita Tributária | K307: Receitas Brutas Realizadas | L307: 8909186.3 | M307: Padrão
C308: Araripina/PE | D308: 2601102 | E308: 2017 | F308: transferencias_correntes_total_brutas | G308: siconfi_dca_araripina_2017.json | H308: DCA-Anexo I-C | I308: RO1.7.0.0.00.00.00 | J308: 1.7.0.0.00.00.00 - Transferências Correntes | K308: Receitas Brutas Realizadas | L308: 1.2635412e+08 | M308: Padrão
C309: Araripina/PE | D309: 2601102 | E309: 2017 | F309: transferencias_capital_total_brutas | G309: siconfi_dca_araripina_2017.json | H309: DCA-Anexo I-C | I309: RO2.4.0.0.00.00.00 | J309: 2.4.0.0.00.00.00 - Transferências de Capital | K309: Receitas Brutas Realizadas | L309: 1126556.7 | M309: Padrão
C310: Araripina/PE | D310: 2601102 | E310: 2017 | F310: transferencias_intergov_correntes_proxy | G310: siconfi_dca_araripina_2017.json | H310: DCA-Anexo I-C | I310: RO1.7.2.0.00.00.00 | J310: 1.7.2.0.00.00.00 - Transferências Intergovernamentais | K310: Receitas Brutas Realizadas | L310: 1.2522438e+08 | M310: Padrão
... C564: Araripina/PE | D564: 2601102 | E564: 2024 | F564: despesa_funcao_28 | G564: siconfi_dca_araripina_2024.json | H564: DCA-Anexo I-E | I564: TotalDespesas | J564: 28 - Encargos Especiais | K564: Despesas Empenhadas | L564: 10373776 | M564: Total Geral da Despesa por Função

Sheet Dados IBGE
C3: Dados-fonte — IBGE/SIDRA
C5: População, PIB municipal e IPCA mensal em formato longo.
C6: População: pessoas; PIB: mil R$ correntes; IPCA: número-índice nacional.
C8: Município | D8: Código IBGE | E8: Ano | F8: Mês | G8: Série | H8: Variável | I8: Unidade | J8: Valor | K8: Arquivo de origem | L8: URL consultada
C9: Arcoverde/PE | D9: 2601201 | E9: 2015 | G9: pop_estimada | H9: População residente estimada | I9: Pessoas | J9: 72625 | K9: ibge_pop_estimativas_2015_2024.json | L9: https://apisidra.ibge.gov.br/values/t/6579/n6/2601201,2601102/v/9324/p/2015-2024
C10: Arcoverde/PE | D10: 2601201 | E10: 2016 | G10: pop_estimada | H10: População residente estimada | I10: Pessoas | J10: 73154 | K10: ibge_pop_estimativas_2015_2024.json | L10: https://apisidra.ibge.gov.br/values/t/6579/n6/2601201,2601102/v/9324/p/2015-2024
C11: Arcoverde/PE | D11: 2601201 | E11: 2017 | G11: pop_estimada | H11: População residente estimada | I11: Pessoas | J11: 73667 | K11: ibge_pop_estimativas_2015_2024.json | L11: https://apisidra.ibge.gov.br/values/t/6579/n6/2601201,2601102/v/9324/p/2015-2024
C12: Arcoverde/PE | D12: 2601201 | E12: 2018 | G12: pop_estimada | H12: População residente estimada | I12: Pessoas | J12: 73844 | K12: ibge_pop_estimativas_2015_2024.json | L12: https://apisidra.ibge.gov.br/values/t/6579/n6/2601201,2601102/v/9324/p/2015-2024
C13: Arcoverde/PE | D13: 2601201 | E13: 2019 | G13: pop_estimada | H13: População residente estimada | I13: Pessoas | J13: 74338 | K13: ibge_pop_estimativas_2015_2024.json | L13: https://apisidra.ibge.gov.br/values/t/6579/n6/2601201,2601102/v/9324/p/2015-2024
C14: Arcoverde/PE | D14: 2601201 | E14: 2020 | G14: pop_estimada | H14: População residente estimada | I14: Pessoas | J14: 74822 | K14: ibge_pop_estimativas_2015_2024.json | L14: https://apisidra.ibge.gov.br/values/t/6579/n6/2601201,2601102/v/9324/p/2015-2024
C15: Arcoverde/PE | D15: 2601201 | E15: 2021 | G15: pop_estimada | H15: População residente estimada | I15: Pessoas | J15: 75295 | K15: ibge_pop_estimativas_2015_2024.json | L15: https://apisidra.ibge.gov.br/values/t/6579/n6/2601201,2601102/v/9324/p/2015-2024
C16: Arcoverde/PE | D16: 2601201 | E16: 2024 | G16: pop_estimada | H16: População residente estimada | I16: Pessoas | J16: 82003 | K16: ibge_pop_estimativas_2015_2024.json | L16: https://apisidra.ibge.gov.br/values/t/6579/n6/2601201,2601102/v/9324/p/2015-2024
C17: Araripina/PE | D17: 2601102 | E17: 2015 | G17: pop_estimada | H17: População residente estimada | I17: Pessoas | J17: 82800 | K17: ibge_pop_estimativas_2015_2024.json | L17: https://apisidra.ibge.gov.br/values/t/6579/n6/2601201,2601102/v/9324/p/2015-2024
C18: Araripina/PE | D18: 2601102 | E18: 2016 | G18: pop_estimada | H18: População residente estimada | I18: Pessoas | J18: 83287 | K18: ibge_pop_estimativas_2015_2024.json | L18: https://apisidra.ibge.gov.br/values/t/6579/n6/2601201,2601102/v/9324/p/2015-2024
C19: Araripina/PE | D19: 2601102 | E19: 2017 | G19: pop_estimada | H19: População residente estimada | I19: Pessoas | J19: 83757 | K19: ibge_pop_estimativas_2015_2024.json | L19: https://apisidra.ibge.gov.br/values/t/6579/n6/2601201,2601102/v/9324/p/2015-2024
C20: Araripina/PE | D20: 2601102 | E20: 2018 | G20: pop_estimada | H20: População residente estimada | I20: Pessoas | J20: 83964 | K20: ibge_pop_estimativas_2015_2024.json | L20: https://apisidra.ibge.gov.br/values/t/6579/n6/2601201,2601102/v/9324/p/2015-2024
... C44: Araripina/PE | D44: 2601102 | E44: 2023 | G44: pib | H44: Produto Interno Bruto a preços correntes | I44: Mil Reais | J44: 1777713 | K44: ibge_pib_municipal_2015_2023.json | L44: https://apisidra.ibge.gov.br/values/t/5938/n6/2601201,2601102/v/37/p/2015-2023
C45: Brasil | D45: 1 | E45: 2015 | F45: 1 | G45: ipca | H45: IPCA - Número-índice (base: dezembro de 1993 = 100) | I45: Número-índice | J45: 4110.2 | K45: ibge_ipca_mensal_2015_2024.json | L45: https://apisidra.ibge.gov.br/values/t/1737/n1/1/v/2266/p/201501-202412
C46: Brasil | D46: 1 | E46: 2015 | F46: 2 | G46: ipca | H46: IPCA - Número-índice (base: dezembro de 1993 = 100) | I46: Número-índice | J46: 4160.34 | K46: ibge_ipca_mensal_2015_2024.json | L46: https://apisidra.ibge.gov.br/values/t/1737/n1/1/v/2266/p/201501-202412
C47: Brasil | D47: 1 | E47: 2015 | F47: 3 | G47: ipca | H47: IPCA - Número-índice (base: dezembro de 1993 = 100) | I47: Número-índice | J47: 4215.26 | K47: ibge_ipca_mensal_2015_2024.json | L47: https://apisidra.ibge.gov.br/values/t/1737/n1/1/v/2266/p/201501-202412
C48: Brasil | D48: 1 | E48: 2015 | F48: 4 | G48: ipca | H48: IPCA - Número-índice (base: dezembro de 1993 = 100) | I48: Número-índice | J48: 4245.19 | K48: ibge_ipca_mensal_2015_2024.json | L48: https://apisidra.ibge.gov.br/values/t/1737/n1/1/v/2266/p/201501-202412
C49: Brasil | D49: 1 | E49: 2015 | F49: 5 | G49: ipca | H49: IPCA - Número-índice (base: dezembro de 1993 = 100) | I49: Número-índice | J49: 4276.6 | K49: ibge_ipca_mensal_2015_2024.json | L49: https://apisidra.ibge.gov.br/values/t/1737/n1/1/v/2266/p/201501-202412
C50: Brasil | D50: 1 | E50: 2015 | F50: 6 | G50: ipca | H50: IPCA - Número-índice (base: dezembro de 1993 = 100) | I50: Número-índice | J50: 4310.39 | K50: ibge_ipca_mensal_2015_2024.json | L50: https://apisidra.ibge.gov.br/values/t/1737/n1/1/v/2266/p/201501-202412
C51: Brasil | D51: 1 | E51: 2015 | F51: 7 | G51: ipca | H51: IPCA - Número-índice (base: dezembro de 1993 = 100) | I51: Número-índice | J51: 4337.11 | K51: ibge_ipca_mensal_2015_2024.json | L51: https://apisidra.ibge.gov.br/values/t/1737/n1/1/v/2266/p/201501-202412
C52: Brasil | D52: 1 | E52: 2015 | F52: 8 | G52: ipca | H52: IPCA - Número-índice (base: dezembro de 1993 = 100) | I52: Número-índice | J52: 4346.65 | K52: ibge_ipca_mensal_2015_2024.json | L52: https://apisidra.ibge.gov.br/values/t/1737/n1/1/v/2266/p/201501-202412
C53: Brasil | D53: 1 | E53: 2015 | F53: 9 | G53: ipca | H53: IPCA - Número-índice (base: dezembro de 1993 = 100) | I53: Número-índice | J53: 4370.12 | K53: ibge_ipca_mensal_2015_2024.json | L53: https://apisidra.ibge.gov.br/values/t/1737/n1/1/v/2266/p/201501-202412
C54: Brasil | D54: 1 | E54: 2015 | F54: 10 | G54: ipca | H54: IPCA - Número-índice (base: dezembro de 1993 = 100) | I54: Número-índice | J54: 4405.95 | K54: ibge_ipca_mensal_2015_2024.json | L54: https://apisidra.ibge.gov.br/values/t/1737/n1/1/v/2266/p/201501-202412
C55: Brasil | D55: 1 | E55: 2015 | F55: 11 | G55: ipca | H55: IPCA - Número-índice (base: dezembro de 1993 = 100) | I55: Número-índice | J55: 4450.45 | K55: ibge_ipca_mensal_2015_2024.json | L55: https://apisidra.ibge.gov.br/values/t/1737/n1/1/v/2266/p/201501-202412
C56: Brasil | D56: 1 | E56: 2015 | F56: 12 | G56: ipca | H56: IPCA - Número-índice (base: dezembro de 1993 = 100) | I56: Número-índice | J56: 4493.17 | K56: ibge_ipca_mensal_2015_2024.json | L56: https://apisidra.ibge.gov.br/values/t/1737/n1/1/v/2266/p/201501-202412
... C164: Brasil | D164: 1 | E164: 2024 | F164: 12 | G164: ipca | H164: IPCA - Número-índice (base: dezembro de 1993 = 100) | I164: Número-índice | J164: 7100.5 | K164: ibge_ipca_mensal_2015_2024.json | L164: https://apisidra.ibge.gov.br/values/t/1737/n1/1/v/2266/p/201501-202412

Sheet Bélgica
C3: Bélgica — governo geral
C5: Eurostat gov_10dd_edpt1; não equiparar a contas municipais brasileiras.
C6: % do PIB; saldo negativo = necessidade líquida de financiamento; dívida é estoque consolidado.
C8: Ano | D8: Saldo de financiamento líquido / PIB | E8: Dívida bruta consolidada / PIB | F8: Setor institucional
C9: 2015 | D9: -2.5 | E9: 105.7 | F9: S13 — Governo geral
C10: 2016 | D10: -2.4 | E10: 105.8 | F10: S13 — Governo geral
C11: 2017 | D11: -0.8 | E11: 102.6 | F11: S13 — Governo geral
C12: 2018 | D12: -1 | E12: 100.2 | F12: S13 — Governo geral
C13: 2019 | D13: -2 | E13: 97.7 | F13: S13 — Governo geral
C14: 2020 | D14: -9 | E14: 111.4 | F14: S13 — Governo geral
C15: 2021 | D15: -5.4 | E15: 108.7 | F15: S13 — Governo geral
C16: 2022 | D16: -3.5 | E16: 103.3 | F16: S13 — Governo geral
C17: 2023 | D17: -4.1 | E17: 102.3 | F17: S13 — Governo geral
C18: 2024 | D18: -4.4 | E18: 104 | F18: S13 — Governo geral
C19: 2025 | D19: -5.2 | E19: 108.1 | F19: S13 — Governo geral

Sheet Cálculos Municipais
C3: Série municipal — fórmulas
C5: Linhas anuais; fórmulas ligam cada indicador às fontes brutas e explicitam a cobertura.
C6: R$ correntes ou R$ médios de 2024 conforme coluna; população em pessoas; razões em %.
C8: Município | D8: Ano | E8: Receita bruta reportada | F8: Dedução FUNDEB | G8: Outras deduções reportadas | H8: Receita líquida após deduções reportadas | I8: Despesa empenhada total | J8: Despesa liquidada total | K8: Despesa paga total | L8: Despesa empenhada exceto intra | M8: Despesa intra residual | N8: Receita tributária própria | O8: Transferências correntes totais | P8: Proxy transferências intergovernamentais correntes | Q8: População | R8: PIB municipal | S8: IPCA média anual | T8: Fator deflator 2024 | U8: Receita bruta real | V8: Despesa empenhada real | W8: Receita real per capita | X8: Despesa real per capita | Y8: Receita tributária / receita bruta | Z8: Transferências correntes / receita bruta | AA8: Receita bruta / PIB | AB8: Despesa empenhada / PIB | AC8: Receita exceto intra | AD8: Receita intra
C9: Arcoverde/PE | D9: 2015 | E9: =IF(COUNTIFS('Dados DCA'!$C$9:$C$564,$C9,'Dados DCA'!$E$9:$E$564,$D9,'Dados DCA'!$F$9:$F$564,"receita_total_bruta")=0,"",SUMIFS('Dados DCA'!$L$9:$L$564,'Dados DCA'!$C$9:$C$564,$C9,'Dados DCA'!$E$9:$E$564,$D9,'Dados DCA'!$F$9:$F$564,"receita_total_bruta")) -> 1.302675e+08 | F9: =IF(COUNTIFS('Dados DCA'!$C$9:$C$564,$C9,'Dados DCA'!$E$9:$E$564,$D9,'Dados DCA'!$F$9:$F$564,"deducao_fundeb")=0,"",ABS(SUMIFS('Dados DCA'!$L$9:$L$564,'Dados DCA'!$C$9:$C$564,$C9,'Dados DCA'!$E$9:$E$564,$D9,'Dados DCA'!$F$9:$F$564,"deducao_fundeb"))) -> 10228661 | G9: =IF(COUNTIFS('Dados DCA'!$C$9:$C$564,$C9,'Dados DCA'!$E$9:$E$564,$D9,'Dados DCA'!$F$9:$F$564,"outras_deducoes")=0,"",ABS(SUMIFS('Dados DCA'!$L$9:$L$564,'Dados DCA'!$C$9:$C$564,$C9,'Dados DCA'!$E$9:$E$564,$D9,'Dados DCA'!$F$9:$F$564,"outras_deducoes"))) | H9: =IF(OR(E9="",F9=""),"",E9-F9-IF(G9="",0,G9)) -> 1.2003884e+08 | I9: =IF(COUNTIFS('Dados DCA'!$C$9:$C$564,$C9,'Dados DCA'!$E$9:$E$564,$D9,'Dados DCA'!$F$9:$F$564,"despesa_empenhada_total")=0,"",SUMIFS('Dados DCA'!$L$9:$L$564,'Dados DCA'!$C$9:$C$564,$C9,'Dados DCA'!$E$9:$E$564,$D9,'Dados DCA'!$F$9:$F$564,"despesa_empenhada_total")) -> 1.2598128e+08 | J9: =IF(COUNTIFS('Dados DCA'!$C$9:$C$564,$C9,'Dados DCA'!$E$9:$E$564,$D9,'Dados DCA'!$F$9:$F$564,"despesa_liquidada_total")=0,"",SUMIFS('Dados DCA'!$L$9:$L$564,'Dados DCA'!$C$9:$C$564,$C9,'Dados DCA'!$E$9:$E$564,$D9,'Dados DCA'!$F$9:$F$564,"despesa_liquidada_total")) -> 1.2598128e+08 | K9: =IF(COUNTIFS('Dados DCA'!$C$9:$C$564,$C9,'Dados DCA'!$E$9:$E$564,$D9,'Dados DCA'!$F$9:$F$564,"despesa_paga_total")=0,"",SUMIFS('Dados DCA'!$L$9:$L$564,'Dados DCA'!$C$9:$C$564,$C9,'Dados DCA'!$E$9:$E$564,$D9,'Dados DCA'!$F$9:$F$564,"despesa_paga_total")) -> 1.2028544e+08 | L9: =IF(COUNTIFS('Dados DCA'!$C$9:$C$564,$C9,'Dados DCA'!$E$9:$E$564,$D9,'Dados DCA'!$F$9:$F$564,"despesa_empenhada_exceto_intra")=0,"",SUMIFS('Dados DCA'!$L$9:$L$564,'Dados DCA'!$C$9:$C$564,$C9,'Dados DCA'!$E$9:$E$564,$D9,'Dados DCA'!$F$9:$F$564,"despesa_empenhada_exceto_intra")) | M9: =IF(OR(I9="",L9=""),"",I9-L9) | N9: =IF(COUNTIFS('Dados DCA'!$C$9:$C$564,$C9,'Dados DCA'!$E$9:$E$564,$D9,'Dados DCA'!$F$9:$F$564,"receita_tributaria_propria_bruta")=0,"",SUMIFS('Dados DCA'!$L$9:$L$564,'Dados DCA'!$C$9:$C$564,$C9,'Dados DCA'!$E$9:$E$564,$D9,'Dados DCA'!$F$9:$F$564,"receita_tributaria_propria_bruta")) -> 11525466 | O9: =IF(COUNTIFS('Dados DCA'!$C$9:$C$564,$C9,'Dados DCA'!$E$9:$E$564,$D9,'Dados DCA'!$F$9:$F$564,"transferencias_correntes_total_brutas")=0,"",SUMIFS('Dados DCA'!$L$9:$L$564,'Dados DCA'!$C$9:$C$564,$C9,'Dados DCA'!$E$9:$E$564,$D9,'Dados DCA'!$F$9:$F$564,"transferencias_correntes_total_brutas")) -> 95184422 | P9: =IF(COUNTIFS('Dados DCA'!$C$9:$C$564,$C9,'Dados DCA'!$E$9:$E$564,$D9,'Dados DCA'!$F$9:$F$564,"transferencias_intergov_correntes_proxy")=0,"",SUMIFS('Dados DCA'!$L$9:$L$564,'Dados DCA'!$C$9:$C$564,$C9,'Dados DCA'!$E$9:$E$564,$D9,'Dados DCA'!$F$9:$F$564,"transferencias_intergov_correntes_proxy")) -> 91796680 | Q9: =IF(COUNTIFS('Dados IBGE'!$C$9:$C$164,$C9,'Dados IBGE'!$E$9:$E$164,$D9,'Dados IBGE'!$G$9:$G$164,"pop_censo")>0,SUMIFS('Dados IBGE'!$J$9:$J$164,'Dados IBGE'!$C$9:$C$164,$C9,'Dados IBGE'!$E$9:$E$164,$D9,'Dados IBGE'!$G$9:$G$164,"pop_censo"),IF(COUNTIFS('Dados IBGE'!$C$9:$C$164,$C9,'Dados IBGE'!$E$9:$E$164,$D9,'Dados IBGE'!$G$9:$G$164,"pop_estimada")=0,"",SUMIFS('Dados IBGE'!$J$9:$J$164,'Dados IBGE'!$C$9:$C$164,$C9,'Dados IBGE'!$E$9:$E$164,$D9,'Dados IBGE'!$G$9:$G$164,"pop_estimada"))) -> 72625 | R9: =IF(COUNTIFS('Dados IBGE'!$C$9:$C$164,$C9,'Dados IBGE'!$E$9:$E$164,$D9,'Dados IBGE'!$G$9:$G$164,"pib")=0,"",SUMIFS('Dados IBGE'!$J$9:$J$164,'Dados IBGE'!$C$9:$C$164,$C9,'Dados IBGE'!$E$9:$E$164,$D9,'Dados IBGE'!$G$9:$G$164,"pib")*1000) -> 803846000 | S9: =IF(COUNTIFS('Dados IBGE'!$E$9:$E$164,$D9,'Dados IBGE'!$G$9:$G$164,"ipca")<>12,"",SUMIFS('Dados IBGE'!$J$9:$J$164,'Dados IBGE'!$E$9:$E$164,$D9,'Dados IBGE'!$G$9:$G$164,"ipca")/12) -> 4310.1192 | T9: =IF(OR(S9="",S9=0),"",AVERAGEIFS('Dados IBGE'!$J$9:$J$164,'Dados IBGE'!$E$9:$E$164,2024,'Dados IBGE'!$G$9:$G$164,"ipca")/S9) -> 1.6129655 | U9: =IF(OR(E9="",T9=""),"",E9*T9) -> 2.1011698e+08 | V9: =IF(OR(I9="",T9=""),"",I9*T9) -> 2.0320345e+08 | W9: =IF(OR(Q9="",Q9=0,U9=""),"",U9/Q9) -> 2893.177 | X9: =IF(OR(Q9="",Q9=0,V9=""),"",V9/Q9) -> 2797.9821 | Y9: =IF(OR(E9="",E9=0,N9=""),"",N9/E9) -> 0.088475372 | Z9: =IF(OR(E9="",E9=0,O9=""),"",O9/E9) -> 0.73068432 | AA9: =IF(OR(R9="",R9=0,E9=""),"",E9/R9) -> 0.1620553 | AB9: =IF(OR(R9="",R9=0,I9=""),"",I9/R9) -> 0.15672315 | AC9: =IF(COUNTIFS('Dados DCA'!$C$9:$C$564,$C9,'Dados DCA'!$E$9:$E$564,$D9,'Dados DCA'!$F$9:$F$564,"receita_exceto_intra_bruta")=0,"",SUMIFS('Dados DCA'!$L$9:$L$564,'Dados DCA'!$C$9:$C$564,$C9,'Dados DCA'!$E$9:$E$564,$D9,'Dados DCA'!$F$9:$F$564,"receita_exceto_intra_bruta")) | AD9: =IF(COUNTIFS('Dados DCA'!$C$9:$C$564,$C9,'Dados DCA'!$E$9:$E$564,$D9,'Dados DCA'!$F$9:$F$564,"receita_intra_bruta")=0,"",SUMIFS('Dados DCA'!$L$9:$L$564,'Dados DCA'!$C$9:$C$564,$C9,'Dados DCA'!$E$9:$E$564,$D9,'Dados DCA'!$F$9:$F$564,"receita_intra_bruta"))
C10: Arcoverde/PE | D10: 2016 | E10: =IF(COUNTIFS('Dados DCA'!$C$9:$C$564,$C10,'Dados DCA'!$E$9:$E$564,$D10,'Dados DCA'!$F$9:$F$564,"receita_total_bruta")=0,"",SUMIFS('Dados DCA'!$L$9:$L$564,'Dados DCA'!$C$9:$C$564,$C10,'Dados DCA'!$E$9:$E$564,$D10,'Dados DCA'!$F$9:$F$564,"receita_total_bruta")) -> 1.4621232e+08 | F10: =IF(COUNTIFS('Dados DCA'!$C$9:$C$564,$C10,'Dados DCA'!$E$9:$E$564,$D10,'Dados DCA'!$F$9:$F$564,"deducao_fundeb")=0,"",ABS(SUMIFS('Dados DCA'!$L$9:$L$564,'Dados DCA'!$C$9:$C$564,$C10,'Dados DCA'!$E$9:$E$564,$D10,'Dados DCA'!$F$9:$F$564,"deducao_fundeb"))) -> 11514533 | G10: =IF(COUNTIFS('Dados DCA'!$C$9:$C$564,$C10,'Dados DCA'!$E$9:$E$564,$D10,'Dados DCA'!$F$9:$F$564,"outras_deducoes")=0,"",ABS(SUMIFS('Dados DCA'!$L$9:$L$564,'Dados DCA'!$C$9:$C$564,$C10,'Dados DCA'!$E$9:$E$564,$D10,'Dados DCA'!$F$9:$F$564,"outras_deducoes"))) | H10: =IF(OR(E10="",F10=""),"",E10-F10-IF(G10="",0,G10)) -> 1.3469779e+08 | I10: =IF(COUNTIFS('Dados DCA'!$C$9:$C$564,$C10,'Dados DCA'!$E$9:$E$564,$D10,'Dados DCA'!$F$9:$F$564,"despesa_empenhada_total")=0,"",SUMIFS('Dados DCA'!$L$9:$L$564,'Dados DCA'!$C$9:$C$564,$C10,'Dados DCA'!$E$9:$E$564,$D10,'Dados DCA'!$F$9:$F$564,"despesa_empenhada_total")) -> 1.3887861e+08 | J10: =IF(COUNTIFS('Dados DCA'!$C$9:$C$564,$C10,'Dados DCA'!$E$9:$E$564,$D10,'Dados DCA'!$F$9:$F$564,"despesa_liquidada_total")=0,"",SUMIFS('Dados DCA'!$L$9:$L$564,'Dados DCA'!$C$9:$C$564,$C10,'Dados DCA'!$E$9:$E$564,$D10,'Dados DCA'!$F$9:$F$564,"despesa_liquidada_total")) -> 1.3887861e+08 | K10: =IF(COUNTIFS('Dados DCA'!$C$9:$C$564,$C10,'Dados DCA'!$E$9:$E$564,$D10,'Dados DCA'!$F$9:$F$564,"despesa_paga_total")=0,"",SUMIFS('Dados DCA'!$L$9:$L$564,'Dados DCA'!$C$9:$C$564,$C10,'Dados DCA'!$E$9:$E$564,$D10,'Dados DCA'!$F$9:$F$564,"despesa_paga_total")) -> 1.2845444e+08 | L10: =IF(COUNTIFS('Dados DCA'!$C$9:$C$564,$C10,'Dados DCA'!$E$9:$E$564,$D10,'Dados DCA'!$F$9:$F$564,"despesa_empenhada_exceto_intra")=0,"",SUMIFS('Dados DCA'!$L$9:$L$564,'Dados DCA'!$C$9:$C$564,$C10,'Dados DCA'!$E$9:$E$564,$D10,'Dados DCA'!$F$9:$F$564,"despesa_empenhada_exceto_intra")) | M10: =IF(OR(I10="",L10=""),"",I10-L10) | N10: =IF(COUNTIFS('Dados DCA'!$C$9:$C$564,$C10,'Dados DCA'!$E$9:$E$564,$D10,'Dados DCA'!$F$9:$F$564,"receita_tributaria_propria_bruta")=0,"",SUMIFS('Dados DCA'!$L$9:$L$564,'Dados DCA'!$C$9:$C$564,$C10,'Dados DCA'!$E$9:$E$564,$D10,'Dados DCA'!$F$9:$F$564,"receita_tributaria_propria_bruta")) -> 12846711 | O10: =IF(COUNTIFS('Dados DCA'!$C$9:$C$564,$C10,'Dados DCA'!$E$9:$E$564,$D10,'Dados DCA'!$F$9:$F$564,"transferencias_correntes_total_brutas")=0,"",SUMIFS('Dados DCA'!$L$9:$L$564,'Dados DCA'!$C$9:$C$564,$C10,'Dados DCA'!$E$9:$E$564,$D10,'Dados DCA'!$F$9:$F$564,"transferencias_correntes_total_brutas")) -> 1.0679914e+08 | P10: =IF(COUNTIFS('Dados DCA'!$C$9:$C$564,$C10,'Dados DCA'!$E$9:$E$564,$D10,'Dados DCA'!$F$9:$F$564,"transferencias_intergov_correntes_proxy")=0,"",SUMIFS('Dados DCA'!$L$9:$L$564,'Dados DCA'!$C$9:$C$564,$C10,'Dados DCA'!$E$9:$E$564,$D10,'Dados DCA'!$F$9:$F$564,"transferencias_intergov_correntes_proxy")) -> 1.048262e+08 | Q10: =IF(COUNTIFS('Dados IBGE'!$C$9:$C$164,$C10,'Dados IBGE'!$E$9:$E$164,$D10,'Dados IBGE'!$G$9:$G$164,"pop_censo")>0,SUMIFS('Dados IBGE'!$J$9:$J$164,'Dados IBGE'!$C$9:$C$164,$C10,'Dados IBGE'!$E$9:$E$164,$D10,'Dados IBGE'!$G$9:$G$164,"pop_censo"),IF(COUNTIFS('Dados IBGE'!$C$9:$C$164,$C10,'Dados IBGE'!$E$9:$E$164,$D10,'Dados IBGE'!$G$9:$G$164,"pop_estimada")=0,"",SUMIFS('Dados IBGE'!$J$9:$J$164,'Dados IBGE'!$C$9:$C$164,$C10,'Dados IBGE'!$E$9:$E$164,$D10,'Dados IBGE'!$G$9:$G$164,"pop_estimada"))) -> 73154 | R10: =IF(COUNTIFS('Dados IBGE'!$C$9:$C$164,$C10,'Dados IBGE'!$E$9:$E$164,$D10,'Dados IBGE'!$G$9:$G$164,"pib")=0,"",SUMIFS('Dados IBGE'!$J$9:$J$164,'Dados IBGE'!$C$9:$C$164,$C10,'Dados IBGE'!$E$9:$E$164,$D10,'Dados IBGE'!$G$9:$G$164,"pib")*1000) -> 948980000 | S10: =IF(COUNTIFS('Dados IBGE'!$E$9:$E$164,$D10,'Dados IBGE'!$G$9:$G$164,"ipca")<>12,"",SUMIFS('Dados IBGE'!$J$9:$J$164,'Dados IBGE'!$E$9:$E$164,$D10,'Dados IBGE'!$G$9:$G$164,"ipca")/12) -> 4686.7867 | T10: =IF(OR(S10="",S10=0),"",AVERAGEIFS('Dados IBGE'!$J$9:$J$164,'Dados IBGE'!$E$9:$E$164,2024,'Dados IBGE'!$G$9:$G$164,"ipca")/S10) -> 1.4833347 | U10: =IF(OR(E10="",T10=""),"",E10*T10) -> 2.1688181e+08 | V10: =IF(OR(I10="",T10=""),"",I10*T10) -> 2.0600346e+08 | W10: =IF(OR(Q10="",Q10=0,U10=""),"",U10/Q10) -> 2964.7294 | X10: =IF(OR(Q10="",Q10=0,V10=""),"",V10/Q10) -> 2816.0245 | Y10: =IF(OR(E10="",E10=0,N10=""),"",N10/E10) -> 0.087863392 | Z10: =IF(OR(E10="",E10=0,O10=""),"",O10/E10) -> 0.7304387 | AA10: =IF(OR(R10="",R10=0,E10=""),"",E10/R10) -> 0.15407313 | AB10: =IF(OR(R10="",R10=0,I10=""),"",I10/R10) -> 0.14634514 | AC10: =IF(COUNTIFS('Dados DCA'!$C$9:$C$564,$C10,'Dados DCA'!$E$9:$E$564,$D10,'Dados DCA'!$F$9:$F$564,"receita_exceto_intra_bruta")=0,"",SUMIFS('Dados DCA'!$L$9:$L$564,'Dados DCA'!$C$9:$C$564,$C10,'Dados DCA'!$E$9:$E$564,$D10,'Dados DCA'!$F$9:$F$564,"receita_exceto_intra_bruta")) | AD10: =IF(COUNTIFS('Dados DCA'!$C$9:$C$564,$C10,'Dados DCA'!$E$9:$E$564,$D10,'Dados DCA'!$F$9:$F$564,"receita_intra_bruta")=0,"",SUMIFS('Dados DCA'!$L$9:$L$564,'Dados DCA'!$C$9:$C$564,$C10,'Dados DCA'!$E$9:$E$564,$D10,'Dados DCA'!$F$9:$F$564,"receita_intra_bruta"))
C11: Arcoverde/PE | D11: 2017 | E11: =IF(COUNTIFS('Dados DCA'!$C$9:$C$564,$C11,'Dados DCA'!$E$9:$E$564,$D11,'Dados DCA'!$F$9:$F$564,"receita_total_bruta")=0,"",SUMIFS('Dados DCA'!$L$9:$L$564,'Dados DCA'!$C$9:$C$564,$C11,'Dados DCA'!$E$9:$E$564,$D11,'Dados DCA'!$F$9:$F$564,"receita_total_bruta")) -> 1.4729836e+08 | F11: =IF(COUNTIFS('Dados DCA'!$C$9:$C$564,$C11,'Dados DCA'!$E$9:$E$564,$D11,'Dados DCA'!$F$9:$F$564,"deducao_fundeb")=0,"",ABS(SUMIFS('Dados DCA'!$L$9:$L$564,'Dados DCA'!$C$9:$C$564,$C11,'Dados DCA'!$E$9:$E$564,$D11,'Dados DCA'!$F$9:$F$564,"deducao_fundeb"))) -> 11283259 | G11: =IF(COUNTIFS('Dados DCA'!$C$9:$C$564,$C11,'Dados DCA'!$E$9:$E$564,$D11,'Dados DCA'!$F$9:$F$564,"outras_deducoes")=0,"",ABS(SUMIFS('Dados DCA'!$L$9:$L$564,'Dados DCA'!$C$9:$C$564,$C11,'Dados DCA'!$E$9:$E$564,$D11,'Dados DCA'!$F$9:$F$564,"outras_deducoes"))) | H11: =IF(OR(E11="",F11=""),"",E11-F11-IF(G11="",0,G11)) -> 1.360151e+08 | I11: =IF(COUNTIFS('Dados DCA'!$C$9:$C$564,$C11,'Dados DCA'!$E$9:$E$564,$D11,'Dados DCA'!$F$9:$F$564,"despesa_empenhada_total")=0,"",SUMIFS('Dados DCA'!$L$9:$L$564,'Dados DCA'!$C$9:$C$564,$C11,'Dados DCA'!$E$9:$E$564,$D11,'Dados DCA'!$F$9:$F$564,"despesa_empenhada_total")) -> 1.4007055e+08 | J11: =IF(COUNTIFS('Dados DCA'!$C$9:$C$564,$C11,'Dados DCA'!$E$9:$E$564,$D11,'Dados DCA'!$F$9:$F$564,"despesa_liquidada_total")=0,"",SUMIFS('Dados DCA'!$L$9:$L$564,'Dados DCA'!$C$9:$C$564,$C11,'Dados DCA'!$E$9:$E$564,$D11,'Dados DCA'!$F$9:$F$564,"despesa_liquidada_total")) -> 1.4007055e+08 | K11: =IF(COUNTIFS('Dados DCA'!$C$9:$C$564,$C11,'Dados DCA'!$E$9:$E$564,$D11,'Dados DCA'!$F$9:$F$564,"despesa_paga_total")=0,"",SUMIFS('Dados DCA'!$L$9:$L$564,'Dados DCA'!$C$9:$C$564,$C11,'Dados DCA'!$E$9:$E$564,$D11,'Dados DCA'!$F$9:$F$564,"despesa_paga_total")) -> 1.2866128e+08 | L11: =IF(COUNTIFS('Dados DCA'!$C$9:$C$564,$C11,'Dados DCA'!$E$9:$E$564,$D11,'Dados DCA'!$F$9:$F$564,"despesa_empenhada_exceto_intra")=0,"",SUMIFS('Dados DCA'!$L$9:$L$564,'Dados DCA'!$C$9:$C$564,$C11,'Dados DCA'!$E$9:$E$564,$D11,'Dados DCA'!$F$9:$F$564,"despesa_empenhada_exceto_intra")) -> 1.3350634e+08 | M11: =IF(OR(I11="",L11=""),"",I11-L11) -> 6564203.6 | N11: =IF(COUNTIFS('Dados DCA'!$C$9:$C$564,$C11,'Dados DCA'!$E$9:$E$564,$D11,'Dados DCA'!$F$9:$F$564,"receita_tributaria_propria_bruta")=0,"",SUMIFS('Dados DCA'!$L$9:$L$564,'Dados DCA'!$C$9:$C$564,$C11,'Dados DCA'!$E$9:$E$564,$D11,'Dados DCA'!$F$9:$F$564,"receita_tributaria_propria_bruta")) -> 11763761 | O11: =IF(COUNTIFS('Dados DCA'!$C$9:$C$564,$C11,'Dados DCA'!$E$9:$E$564,$D11,'Dados DCA'!$F$9:$F$564,"transferencias_correntes_total_brutas")=0,"",SUMIFS('Dados DCA'!$L$9:$L$564,'Dados DCA'!$C$9:$C$564,$C11,'Dados DCA'!$E$9:$E$564,$D11,'Dados DCA'!$F$9:$F$564,"transferencias_correntes_total_brutas")) -> 1.0632472e+08 | P11: =IF(COUNTIFS('Dados DCA'!$C$9:$C$564,$C11,'Dados DCA'!$E$9:$E$564,$D11,'Dados DCA'!$F$9:$F$564,"transferencias_intergov_correntes_proxy")=0,"",SUMIFS('Dados DCA'!$L$9:$L$564,'Dados DCA'!$C$9:$C$564,$C11,'Dados DCA'!$E$9:$E$564,$D11,'Dados DCA'!$F$9:$F$564,"transferencias_intergov_correntes_proxy")) -> 1.0475739e+08 | Q11: =IF(COUNTIFS('Dados IBGE'!$C$9:$C$164,$C11,'Dados IBGE'!$E$9:$E$164,$D11,'Dados IBGE'!$G$9:$G$164,"pop_censo")>0,SUMIFS('Dados IBGE'!$J$9:$J$164,'Dados IBGE'!$C$9:$C$164,$C11,'Dados IBGE'!$E$9:$E$164,$D11,'Dados IBGE'!$G$9:$G$164,"pop_censo"),IF(COUNTIFS('Dados IBGE'!$C$9:$C$164,$C11,'Dados IBGE'!$E$9:$E$164,$D11,'Dados IBGE'!$G$9:$G$164,"pop_estimada")=0,"",SUMIFS('Dados IBGE'!$J$9:$J$164,'Dados IBGE'!$C$9:$C$164,$C11,'Dados IBGE'!$E$9:$E$164,$D11,'Dados IBGE'!$G$9:$G$164,"pop_estimada"))) -> 73667 | R11: =IF(COUNTIFS('Dados IBGE'!$C$9:$C$164,$C11,'Dados IBGE'!$E$9:$E$164,$D11,'Dados IBGE'!$G$9:$G$164,"pib")=0,"",SUMIFS('Dados IBGE'!$J$9:$J$164,'Dados IBGE'!$C$9:$C$164,$C11,'Dados IBGE'!$E$9:$E$164,$D11,'Dados IBGE'!$G$9:$G$164,"pib")*1000) -> 977866000 | S11: =IF(COUNTIFS('Dados IBGE'!$E$9:$E$164,$D11,'Dados IBGE'!$G$9:$G$164,"ipca")<>12,"",SUMIFS('Dados IBGE'!$J$9:$J$164,'Dados IBGE'!$E$9:$E$164,$D11,'Dados IBGE'!$G$9:$G$164,"ipca")/12) -> 4848.3108 | T11: =IF(OR(S11="",S11=0),"",AVERAGEIFS('Dados IBGE'!$J$9:$J$164,'Dados IBGE'!$E$9:$E$164,2024,'Dados IBGE'!$G$9:$G$164,"ipca")/S11) -> 1.4339166 | U11: =IF(OR(E11="",T11=""),"",E11*T11) -> 2.1121356e+08 | V11: =IF(OR(I11="",T11=""),"",I11*T11) -> 2.0084948e+08 | W11: =IF(OR(Q11="",Q11=0,U11=""),"",U11/Q11) -> 2867.1394 | X11: =IF(OR(Q11="",Q11=0,V11=""),"",V11/Q11) -> 2726.4512 | Y11: =IF(OR(E11="",E11=0,N11=""),"",N11/E11) -> 0.079863492 | Z11: =IF(OR(E11="",E11=0,O11=""),"",O11/E11) -> 0.72183236 | AA11: =IF(OR(R11="",R11=0,E11=""),"",E11/R11) -> 0.15063246 | AB11: =IF(OR(R11="",R11=0,I11=""),"",I11/R11) -> 0.14324104 | AC11: =IF(COUNTIFS('Dados DCA'!$C$9:$C$564,$C11,'Dados DCA'!$E$9:$E$564,$D11,'Dados DCA'!$F$9:$F$564,"receita_exceto_intra_bruta")=0,"",SUMIFS('Dados DCA'!$L$9:$L$564,'Dados DCA'!$C$9:$C$564,$C11,'Dados DCA'!$E$9:$E$564,$D11,'Dados DCA'!$F$9:$F$564,"receita_exceto_intra_bruta")) | AD11: =IF(COUNTIFS('Dados DCA'!$C$9:$C$564,$C11,'Dados DCA'!$E$9:$E$564,$D11,'Dados DCA'!$F$9:$F$564,"receita_intra_bruta")=0,"",SUMIFS('Dados DCA'!$L$9:$L$564,'Dados DCA'!$C$9:$C$564,$C11,'Dados DCA'!$E$9:$E$564,$D11,'Dados DCA'!$F$9:$F$564,"receita_intra_bruta"))
C12: Arcoverde/PE | D12: 2018 | E12: =IF(COUNTIFS('Dados DCA'!$C$9:$C$564,$C12,'Dados DCA'!$E$9:$E$564,$D12,'Dados DCA'!$F$9:$F$564,"receita_total_bruta")=0,"",SUMIFS('Dados DCA'!$L$9:$L$564,'Dados DCA'!$C$9:$C$564,$C12,'Dados DCA'!$E$9:$E$564,$D12,'Dados DCA'!$F$9:$F$564,"receita_total_bruta")) -> 1.5745488e+08 | F12: =IF(COUNTIFS('Dados DCA'!$C$9:$C$564,$C12,'Dados DCA'!$E$9:$E$564,$D12,'Dados DCA'!$F$9:$F$564,"deducao_fundeb")=0,"",ABS(SUMIFS('Dados DCA'!$L$9:$L$564,'Dados DCA'!$C$9:$C$564,$C12,'Dados DCA'!$E$9:$E$564,$D12,'Dados DCA'!$F$9:$F$564,"deducao_fundeb"))) -> 12079304 | G12: =IF(COUNTIFS('Dados DCA'!$C$9:$C$564,$C12,'Dados DCA'!$E$9:$E$564,$D12,'Dados DCA'!$F$9:$F$564,"outras_deducoes")=0,"",ABS(SUMIFS('Dados DCA'!$L$9:$L$564,'Dados DCA'!$C$9:$C$564,$C12,'Dados DCA'!$E$9:$E$564,$D12,'Dados DCA'!$F$9:$F$564,"outras_deducoes"))) | H12: =IF(OR(E12="",F12=""),"",E12-F12-IF(G12="",0,G12)) -> 1.4537558e+08 | I12: =IF(COUNTIFS('Dados DCA'!$C$9:$C$564,$C12,'Dados DCA'!$E$9:$E$564,$D12,'Dados DCA'!$F$9:$F$564,"despesa_empenhada_total")=0,"",SUMIFS('Dados DCA'!$L$9:$L$564,'Dados DCA'!$C$9:$C$564,$C12,'Dados DCA'!$E$9:$E$564,$D12,'Dados DCA'!$F$9:$F$564,"despesa_empenhada_total")) -> 1.4908602e+08 | J12: =IF(COUNTIFS('Dados DCA'!$C$9:$C$564,$C12,'Dados DCA'!$E$9:$E$564,$D12,'Dados DCA'!$F$9:$F$564,"despesa_liquidada_total")=0,"",SUMIFS('Dados DCA'!$L$9:$L$564,'Dados DCA'!$C$9:$C$564,$C12,'Dados DCA'!$E$9:$E$564,$D12,'Dados DCA'!$F$9:$F$564,"despesa_liquidada_total")) -> 1.4908602e+08 | K12: =IF(COUNTIFS('Dados DCA'!$C$9:$C$564,$C12,'Dados DCA'!$E$9:$E$564,$D12,'Dados DCA'!$F$9:$F$564,"despesa_paga_total")=0,"",SUMIFS('Dados DCA'!$L$9:$L$564,'Dados DCA'!$C$9:$C$564,$C12,'Dados DCA'!$E$9:$E$564,$D12,'Dados DCA'!$F$9:$F$564,"despesa_paga_total")) -> 1.4005725e+08 | L12: =IF(COUNTIFS('Dados DCA'!$C$9:$C$564,$C12,'Dados DCA'!$E$9:$E$564,$D12,'Dados DCA'!$F$9:$F$564,"despesa_empenhada_exceto_intra")=0,"",SUMIFS('Dados DCA'!$L$9:$L$564,'Dados DCA'!$C$9:$C$564,$C12,'Dados DCA'!$E$9:$E$564,$D12,'Dados DCA'!$F$9:$F$564,"despesa_empenhada_exceto_intra")) -> 1.4264365e+08 | M12: =IF(OR(I12="",L12=""),"",I12-L12) -> 6442376.8 | N12: =IF(COUNTIFS('Dados DCA'!$C$9:$C$564,$C12,'Dados DCA'!$E$9:$E$564,$D12,'Dados DCA'!$F$9:$F$564,"receita_tributaria_propria_bruta")=0,"",SUMIFS('Dados DCA'!$L$9:$L$564,'Dados DCA'!$C$9:$C$564,$C12,'Dados DCA'!$E$9:$E$564,$D12,'Dados DCA'!$F$9:$F$564,"receita_tributaria_propria_bruta")) -> 13412964 | O12: =IF(COUNTIFS('Dados DCA'!$C$9:$C$564,$C12,'Dados DCA'!$E$9:$E$564,$D12,'Dados DCA'!$F$9:$F$564,"transferencias_correntes_total_brutas")=0,"",SUMIFS('Dados DCA'!$L$9:$L$564,'Dados DCA'!$C$9:$C$564,$C12,'Dados DCA'!$E$9:$E$564,$D12,'Dados DCA'!$F$9:$F$564,"transferencias_correntes_total_brutas")) -> 1.1475123e+08 | P12: =IF(COUNTIFS('Dados DCA'!$C$9:$C$564,$C12,'Dados DCA'!$E$9:$E$564,$D12,'Dados DCA'!$F$9:$F$564,"transferencias_intergov_correntes_proxy")=0,"",SUMIFS('Dados DCA'!$L$9:$L$564,'Dados DCA'!$C$9:$C$564,$C12,'Dados DCA'!$E$9:$E$564,$D12,'Dados DCA'!$F$9:$F$564,"transferencias_intergov_correntes_proxy")) -> 90386381 | Q12: =IF(COUNTIFS('Dados IBGE'!$C$9:$C$164,$C12,'Dados IBGE'!$E$9:$E$164,$D12,'Dados IBGE'!$G$9:$G$164,"pop_censo")>0,SUMIFS('Dados IBGE'!$J$9:$J$164,'Dados IBGE'!$C$9:$C$164,$C12,'Dados IBGE'!$E$9:$E$164,$D12,'Dados IBGE'!$G$9:$G$164,"pop_censo"),IF(COUNTIFS('Dados IBGE'!$C$9:$C$164,$C12,'Dados IBGE'!$E$9:$E$164,$D12,'Dados IBGE'!$G$9:$G$164,"pop_estimada")=0,"",SUMIFS('Dados IBGE'!$J$9:$J$164,'Dados IBGE'!$C$9:$C$164,$C12,'Dados IBGE'!$E$9:$E$164,$D12,'Dados IBGE'!$G$9:$G$164,"pop_estimada"))) -> 73844 | R12: =IF(COUNTIFS('Dados IBGE'!$C$9:$C$164,$C12,'Dados IBGE'!$E$9:$E$164,$D12,'Dados IBGE'!$G$9:$G$164,"pib")=0,"",SUMIFS('Dados IBGE'!$J$9:$J$164,'Dados IBGE'!$C$9:$C$164,$C12,'Dados IBGE'!$E$9:$E$164,$D12,'Dados IBGE'!$G$9:$G$164,"pib")*1000) -> 1007779000 | S12: =IF(COUNTIFS('Dados IBGE'!$E$9:$E$164,$D12,'Dados IBGE'!$G$9:$G$164,"ipca")<>12,"",SUMIFS('Dados IBGE'!$J$9:$J$164,'Dados IBGE'!$E$9:$E$164,$D12,'Dados IBGE'!$G$9:$G$164,"ipca")/12) -> 5025.9942 | T12: =IF(OR(S12="",S12=0),"",AVERAGEIFS('Dados IBGE'!$J$9:$J$164,'Dados IBGE'!$E$9:$E$164,2024,'Dados IBGE'!$G$9:$G$164,"ipca")/S12) -> 1.3832235 | U12: =IF(OR(E12="",T12=""),"",E12*T12) -> 2.177953e+08 | V12: =IF(OR(I12="",T12=""),"",I12*T12) -> 2.0621929e+08 | W12: =IF(OR(Q12="",Q12=0,U12=""),"",U12/Q12) -> 2949.3973 | X12: =IF(OR(Q12="",Q12=0,V12=""),"",V12/Q12) -> 2792.6344 | Y12: =IF(OR(E12="",E12=0,N12=""),"",N12/E12) -> 0.085186082 | Z12: =IF(OR(E12="",E12=0,O12=""),"",O12/E12) -> 0.72878799 | AA12: =IF(OR(R12="",R12=0,E12=""),"",E12/R12) -> 0.15623949 | AB12: =IF(OR(R12="",R12=0,I12=""),"",I12/R12) -> 0.14793523 | AC12: =IF(COUNTIFS('Dados DCA'!$C$9:$C$564,$C12,'Dados DCA'!$E$9:$E$564,$D12,'Dados DCA'!$F$9:$F$564,"receita_exceto_intra_bruta")=0,"",SUMIFS('Dados DCA'!$L$9:$L$564,'Dados DCA'!$C$9:$C$564,$C12,'Dados DCA'!$E$9:$E$564,$D12,'Dados DCA'!$F$9:$F$564,"receita_exceto_intra_bruta")) | AD12: =IF(COUNTIFS('Dados DCA'!$C$9:$C$564,$C12,'Dados DCA'!$E$9:$E$564,$D12,'Dados DCA'!$F$9:$F$564,"receita_intra_bruta")=0,"",SUMIFS('Dados DCA'!$L$9:$L$564,'Dados DCA'!$C$9:$C$564,$C12,'Dados DCA'!$E$9:$E$564,$D12,'Dados DCA'!$F$9:$F$564,"receita_intra_bruta"))
C13: Arcoverde/PE | D13: 2019 | E13: =IF(COUNTIFS('Dados DCA'!$C$9:$C$564,$C13,'Dados DCA'!$E$9:$E$564,$D13,'Dados DCA'!$F$9:$F$564,"receita_total_bruta")=0,"",SUMIFS('Dados DCA'!$L$9:$L$564,'Dados DCA'!$C$9:$C$564,$C13,'Dados DCA'!$E$9:$E$564,$D13,'Dados DCA'!$F$9:$F$564,"receita_total_bruta")) -> 1.7582532e+08 | F13: =IF(COUNTIFS('Dados DCA'!$C$9:$C$564,$C13,'Dados DCA'!$E$9:$E$564,$D13,'Dados DCA'!$F$9:$F$564,"deducao_fundeb")=0,"",ABS(SUMIFS('Dados DCA'!$L$9:$L$564,'Dados DCA'!$C$9:$C$564,$C13,'Dados DCA'!$E$9:$E$564,$D13,'Dados DCA'!$F$9:$F$564,"deducao_fundeb"))) -> 13092008 | G13: =IF(COUNTIFS('Dados DCA'!$C$9:$C$564,$C13,'Dados DCA'!$E$9:$E$564,$D13,'Dados DCA'!$F$9:$F$564,"outras_deducoes")=0,"",ABS(SUMIFS('Dados DCA'!$L$9:$L$564,'Dados DCA'!$C$9:$C$564,$C13,'Dados DCA'!$E$9:$E$564,$D13,'Dados DCA'!$F$9:$F$564,"outras_deducoes"))) | H13: =IF(OR(E13="",F13=""),"",E13-F13-IF(G13="",0,G13)) -> 1.6273331e+08 | I13: =IF(COUNTIFS('Dados DCA'!$C$9:$C$564,$C13,'Dados DCA'!$E$9:$E$564,$D13,'Dados DCA'!$F$9:$F$564,"despesa_empenhada_total")=0,"",SUMIFS('Dados DCA'!$L$9:$L$564,'Dados DCA'!$C$9:$C$564,$C13,'Dados DCA'!$E$9:$E$564,$D13,'Dados DCA'!$F$9:$F$564,"despesa_empenhada_total")) -> 1.6117579e+08 | J13: =IF(COUNTIFS('Dados DCA'!$C$9:$C$564,$C13,'Dados DCA'!$E$9:$E$564,$D13,'Dados DCA'!$F$9:$F$564,"despesa_liquidada_total")=0,"",SUMIFS('Dados DCA'!$L$9:$L$564,'Dados DCA'!$C$9:$C$564,$C13,'Dados DCA'!$E$9:$E$564,$D13,'Dados DCA'!$F$9:$F$564,"despesa_liquidada_total")) -> 1.6117579e+08 | K13: =IF(COUNTIFS('Dados DCA'!$C$9:$C$564,$C13,'Dados DCA'!$E$9:$E$564,$D13,'Dados DCA'!$F$9:$F$564,"despesa_paga_total")=0,"",SUMIFS('Dados DCA'!$L$9:$L$564,'Dados DCA'!$C$9:$C$564,$C13,'Dados DCA'!$E$9:$E$564,$D13,'Dados DCA'!$F$9:$F$564,"despesa_paga_total")) -> 1.5446288e+08 | L13: =IF(COUNTIFS('Dados DCA'!$C$9:$C$564,$C13,'Dados DCA'!$E$9:$E$564,$D13,'Dados DCA'!$F$9:$F$564,"despesa_empenhada_exceto_intra")=0,"",SUMIFS('Dados DCA'!$L$9:$L$564,'Dados DCA'!$C$9:$C$564,$C13,'Dados DCA'!$E$9:$E$564,$D13,'Dados DCA'!$F$9:$F$564,"despesa_empenhada_exceto_intra")) -> 1.544738e+08 | M13: =IF(OR(I13="",L13=""),"",I13-L13) -> 6701997.3 | N13: =IF(COUNTIFS('Dados DCA'!$C$9:$C$564,$C13,'Dados DCA'!$E$9:$E$564,$D13,'Dados DCA'!$F$9:$F$564,"receita_tributaria_propria_bruta")=0,"",SUMIFS('Dados DCA'!$L$9:$L$564,'Dados DCA'!$C$9:$C$564,$C13,'Dados DCA'!$E$9:$E$564,$D13,'Dados DCA'!$F$9:$F$564,"receita_tributaria_propria_bruta")) -> 16534029 | O13: =IF(COUNTIFS('Dados DCA'!$C$9:$C$564,$C13,'Dados DCA'!$E$9:$E$564,$D13,'Dados DCA'!$F$9:$F$564,"transferencias_correntes_total_brutas")=0,"",SUMIFS('Dados DCA'!$L$9:$L$564,'Dados DCA'!$C$9:$C$564,$C13,'Dados DCA'!$E$9:$E$564,$D13,'Dados DCA'!$F$9:$F$564,"transferencias_correntes_total_brutas")) -> 1.2699682e+08 | P13: =IF(COUNTIFS('Dados DCA'!$C$9:$C$564,$C13,'Dados DCA'!$E$9:$E$564,$D13,'Dados DCA'!$F$9:$F$564,"transferencias_intergov_correntes_proxy")=0,"",SUMIFS('Dados DCA'!$L$9:$L$564,'Dados DCA'!$C$9:$C$564,$C13,'Dados DCA'!$E$9:$E$564,$D13,'Dados DCA'!$F$9:$F$564,"transferencias_intergov_correntes_proxy")) -> 1.0220891e+08 | Q13: =IF(COUNTIFS('Dados IBGE'!$C$9:$C$164,$C13,'Dados IBGE'!$E$9:$E$164,$D13,'Dados IBGE'!$G$9:$G$164,"pop_censo")>0,SUMIFS('Dados IBGE'!$J$9:$J$164,'Dados IBGE'!$C$9:$C$164,$C13,'Dados IBGE'!$E$9:$E$164,$D13,'Dados IBGE'!$G$9:$G$164,"pop_censo"),IF(COUNTIFS('Dados IBGE'!$C$9:$C$164,$C13,'Dados IBGE'!$E$9:$E$164,$D13,'Dados IBGE'!$G$9:$G$164,"pop_estimada")=0,"",SUMIFS('Dados IBGE'!$J$9:$J$164,'Dados IBGE'!$C$9:$C$164,$C13,'Dados IBGE'!$E$9:$E$164,$D13,'Dados IBGE'!$G$9:$G$164,"pop_estimada"))) -> 74338 | R13: =IF(COUNTIFS('Dados IBGE'!$C$9:$C$164,$C13,'Dados IBGE'!$E$9:$E$164,$D13,'Dados IBGE'!$G$9:$G$164,"pib")=0,"",SUMIFS('Dados IBGE'!$J$9:$J$164,'Dados IBGE'!$C$9:$C$164,$C13,'Dados IBGE'!$E$9:$E$164,$D13,'Dados IBGE'!$G$9:$G$164,"pib")*1000) -> 1054119000 | S13: =IF(COUNTIFS('Dados IBGE'!$E$9:$E$164,$D13,'Dados IBGE'!$G$9:$G$164,"ipca")<>12,"",SUMIFS('Dados IBGE'!$J$9:$J$164,'Dados IBGE'!$E$9:$E$164,$D13,'Dados IBGE'!$G$9:$G$164,"ipca")/12) -> 5213.6133 | T13: =IF(OR(S13="",S13=0),"",AVERAGEIFS('Dados IBGE'!$J$9:$J$164,'Dados IBGE'!$E$9:$E$164,2024,'Dados IBGE'!$G$9:$G$164,"ipca")/S13) -> 1.3334463 | U13: =IF(OR(E13="",T13=""),"",E13*T13) -> 2.3445361e+08 | V13: =IF(OR(I13="",T13=""),"",I13*T13) -> 2.1491926e+08 | W13: =IF(OR(Q13="",Q13=0,U13=""),"",U13/Q13) -> 3153.8865 | X13: =IF(OR(Q13="",Q13=0,V13=""),"",V13/Q13) -> 2891.109 | Y13: =IF(OR(E13="",E13=0,N13=""),"",N13/E13) -> 0.094036683 | Z13: =IF(OR(E13="",E13=0,O13=""),"",O13/E13) -> 0.72228976 | AA13: =IF(OR(R13="",R13=0,E13=""),"",E13/R13) -> 0.16679836 | AB13: =IF(OR(R13="",R13=0,I13=""),"",I13/R13) -> 0.15290095 | AC13: =IF(COUNTIFS('Dados DCA'!$C$9:$C$564,$C13,'Dados DCA'!$E$9:$E$564,$D13,'Dados DCA'!$F$9:$F$564,"receita_exceto_intra_bruta")=0,"",SUMIFS('Dados DCA'!$L$9:$L$564,'Dados DCA'!$C$9:$C$564,$C13,'Dados DCA'!$E$9:$E$564,$D13,'Dados DCA'!$F$9:$F$564,"receita_exceto_intra_bruta")) -> 1.6892543e+08 | AD13: =IF(COUNTIFS('Dados DCA'!$C$9:$C$564,$C13,'Dados DCA'!$E$9:$E$564,$D13,'Dados DCA'!$F$9:$F$564,"receita_intra_bruta")=0,"",SUMIFS('Dados DCA'!$L$9:$L$564,'Dados DCA'!$C$9:$C$564,$C13,'Dados DCA'!$E$9:$E$564,$D13,'Dados DCA'!$F$9:$F$564,"receita_intra_bruta")) -> 6899889.6
C14: Arcoverde/PE | D14: 2020 | E14: =IF(COUNTIFS('Dados DCA'!$C$9:$C$564,$C14,'Dados DCA'!$E$9:$E$564,$D14,'Dados DCA'!$F$9:$F$564,"receita_total_bruta")=0,"",SUMIFS('Dados DCA'!$L$9:$L$564,'Dados DCA'!$C$9:$C$564,$C14,'Dados DCA'!$E$9:$E$564,$D14,'Dados DCA'!$F$9:$F$564,"receita_total_bruta")) -> 1.9433145e+08 | F14: =IF(COUNTIFS('Dados DCA'!$C$9:$C$564,$C14,'Dados DCA'!$E$9:$E$564,$D14,'Dados DCA'!$F$9:$F$564,"deducao_fundeb")=0,"",ABS(SUMIFS('Dados DCA'!$L$9:$L$564,'Dados DCA'!$C$9:$C$564,$C14,'Dados DCA'!$E$9:$E$564,$D14,'Dados DCA'!$F$9:$F$564,"deducao_fundeb"))) -> 12332254 | G14: =IF(COUNTIFS('Dados DCA'!$C$9:$C$564,$C14,'Dados DCA'!$E$9:$E$564,$D14,'Dados DCA'!$F$9:$F$564,"outras_deducoes")=0,"",ABS(SUMIFS('Dados DCA'!$L$9:$L$564,'Dados DCA'!$C$9:$C$564,$C14,'Dados DCA'!$E$9:$E$564,$D14,'Dados DCA'!$F$9:$F$564,"outras_deducoes"))) | H14: =IF(OR(E14="",F14=""),"",E14-F14-IF(G14="",0,G14)) -> 1.819992e+08 | I14: =IF(COUNTIFS('Dados DCA'!$C$9:$C$564,$C14,'Dados DCA'!$E$9:$E$564,$D14,'Dados DCA'!$F$9:$F$564,"despesa_empenhada_total")=0,"",SUMIFS('Dados DCA'!$L$9:$L$564,'Dados DCA'!$C$9:$C$564,$C14,'Dados DCA'!$E$9:$E$564,$D14,'Dados DCA'!$F$9:$F$564,"despesa_empenhada_total")) -> 1.9486752e+08 | J14: =IF(COUNTIFS('Dados DCA'!$C$9:$C$564,$C14,'Dados DCA'!$E$9:$E$564,$D14,'Dados DCA'!$F$9:$F$564,"despesa_liquidada_total")=0,"",SUMIFS('Dados DCA'!$L$9:$L$564,'Dados DCA'!$C$9:$C$564,$C14,'Dados DCA'!$E$9:$E$564,$D14,'Dados DCA'!$F$9:$F$564,"despesa_liquidada_total")) -> 1.9486752e+08 | K14: =IF(COUNTIFS('Dados DCA'!$C$9:$C$564,$C14,'Dados DCA'!$E$9:$E$564,$D14,'Dados DCA'!$F$9:$F$564,"despesa_paga_total")=0,"",SUMIFS('Dados DCA'!$L$9:$L$564,'Dados DCA'!$C$9:$C$564,$C14,'Dados DCA'!$E$9:$E$564,$D14,'Dados DCA'!$F$9:$F$564,"despesa_paga_total")) -> 1.8948923e+08 | L14: =IF(COUNTIFS('Dados DCA'!$C$9:$C$564,$C14,'Dados DCA'!$E$9:$E$564,$D14,'Dados DCA'!$F$9:$F$564,"despesa_empenhada_exceto_intra")=0,"",SUMIFS('Dados DCA'!$L$9:$L$564,'Dados DCA'!$C$9:$C$564,$C14,'Dados DCA'!$E$9:$E$564,$D14,'Dados DCA'!$F$9:$F$564,"despesa_empenhada_exceto_intra")) -> 1.8713471e+08 | M14: =IF(OR(I14="",L14=""),"",I14-L14) -> 7732809 | N14: =IF(COUNTIFS('Dados DCA'!$C$9:$C$564,$C14,'Dados DCA'!$E$9:$E$564,$D14,'Dados DCA'!$F$9:$F$564,"receita_tributaria_propria_bruta")=0,"",SUMIFS('Dados DCA'!$L$9:$L$564,'Dados DCA'!$C$9:$C$564,$C14,'Dados DCA'!$E$9:$E$564,$D14,'Dados DCA'!$F$9:$F$564,"receita_tributaria_propria_bruta")) -> 18667003 | O14: =IF(COUNTIFS('Dados DCA'!$C$9:$C$564,$C14,'Dados DCA'!$E$9:$E$564,$D14,'Dados DCA'!$F$9:$F$564,"transferencias_correntes_total_brutas")=0,"",SUMIFS('Dados DCA'!$L$9:$L$564,'Dados DCA'!$C$9:$C$564,$C14,'Dados DCA'!$E$9:$E$564,$D14,'Dados DCA'!$F$9:$F$564,"transferencias_correntes_total_brutas")) -> 1.3973485e+08 | P14: =IF(COUNTIFS('Dados DCA'!$C$9:$C$564,$C14,'Dados DCA'!$E$9:$E$564,$D14,'Dados DCA'!$F$9:$F$564,"transferencias_intergov_correntes_proxy")=0,"",SUMIFS('Dados DCA'!$L$9:$L$564,'Dados DCA'!$C$9:$C$564,$C14,'Dados DCA'!$E$9:$E$564,$D14,'Dados DCA'!$F$9:$F$564,"transferencias_intergov_correntes_proxy")) -> 1.1337803e+08 | Q14: =IF(COUNTIFS('Dados IBGE'!$C$9:$C$164,$C14,'Dados IBGE'!$E$9:$E$164,$D14,'Dados IBGE'!$G$9:$G$164,"pop_censo")>0,SUMIFS('Dados IBGE'!$J$9:$J$164,'Dados IBGE'!$C$9:$C$164,$C14,'Dados IBGE'!$E$9:$E$164,$D14,'Dados IBGE'!$G$9:$G$164,"pop_censo"),IF(COUNTIFS('Dados IBGE'!$C$9:$C$164,$C14,'Dados IBGE'!$E$9:$E$164,$D14,'Dados IBGE'!$G$9:$G$164,"pop_estimada")=0,"",SUMIFS('Dados IBGE'!$J$9:$J$164,'Dados IBGE'!$C$9:$C$164,$C14,'Dados IBGE'!$E$9:$E$164,$D14,'Dados IBGE'!$G$9:$G$164,"pop_estimada"))) -> 74822 | R14: =IF(COUNTIFS('Dados IBGE'!$C$9:$C$164,$C14,'Dados IBGE'!$E$9:$E$164,$D14,'Dados IBGE'!$G$9:$G$164,"pib")=0,"",SUMIFS('Dados IBGE'!$J$9:$J$164,'Dados IBGE'!$C$9:$C$164,$C14,'Dados IBGE'!$E$9:$E$164,$D14,'Dados IBGE'!$G$9:$G$164,"pib")*1000) -> 1240609000 | S14: =IF(COUNTIFS('Dados IBGE'!$E$9:$E$164,$D14,'Dados IBGE'!$G$9:$G$164,"ipca")<>12,"",SUMIFS('Dados IBGE'!$J$9:$J$164,'Dados IBGE'!$E$9:$E$164,$D14,'Dados IBGE'!$G$9:$G$164,"ipca")/12) -> 5381.0625 | T14: =IF(OR(S14="",S14=0),"",AVERAGEIFS('Dados IBGE'!$J$9:$J$164,'Dados IBGE'!$E$9:$E$164,2024,'Dados IBGE'!$G$9:$G$164,"ipca")/S14) -> 1.2919518 | U14: =IF(OR(E14="",T14=""),"",E14*T14) -> 2.5106686e+08 | V14: =IF(OR(I14="",T14=""),"",I14*T14) -> 2.5175945e+08 | W14: =IF(OR(Q14="",Q14=0,U14=""),"",U14/Q14) -> 3355.522 | X14: =IF(OR(Q14="",Q14=0,V14=""),"",V14/Q14) -> 3364.7783 | Y14: =IF(OR(E14="",E14=0,N14=""),"",N14/E14) -> 0.09605755 | Z14: =IF(OR(E14="",E14=0,O14=""),"",O14/E14) -> 0.71905422 | AA14: =IF(OR(R14="",R14=0,E14=""),"",E14/R14) -> 0.15664198 | AB14: =IF(OR(R14="",R14=0,I14=""),"",I14/R14) -> 0.15707408 | AC14: =IF(COUNTIFS('Dados DCA'!$C$9:$C$564,$C14,'Dados DCA'!$E$9:$E$564,$D14,'Dados DCA'!$F$9:$F$564,"receita_exceto_intra_bruta")=0,"",SUMIFS('Dados DCA'!$L$9:$L$564,'Dados DCA'!$C$9:$C$564,$C14,'Dados DCA'!$E$9:$E$564,$D14,'Dados DCA'!$F$9:$F$564,"receita_exceto_intra_bruta")) -> 1.8677365e+08 | AD14: =IF(COUNTIFS('Dados DCA'!$C$9:$C$564,$C14,'Dados DCA'!$E$9:$E$564,$D14,'Dados DCA'!$F$9:$F$564,"receita_intra_bruta")=0,"",SUMIFS('Dados DCA'!$L$9:$L$564,'Dados DCA'!$C$9:$C$564,$C14,'Dados DCA'!$E$9:$E$564,$D14,'Dados DCA'!$F$9:$F$564,"receita_intra_bruta")) -> 7557801.2
C15: Arcoverde/PE | D15: 2021 | E15: =IF(COUNTIFS('Dados DCA'!$C$9:$C$564,$C15,'Dados DCA'!$E$9:$E$564,$D15,'Dados DCA'!$F$9:$F$564,"receita_total_bruta")=0,"",SUMIFS('Dados DCA'!$L$9:$L$564,'Dados DCA'!$C$9:$C$564,$C15,'Dados DCA'!$E$9:$E$564,$D15,'Dados DCA'!$F$9:$F$564,"receita_total_bruta")) -> 2.1601596e+08 | F15: =IF(COUNTIFS('Dados DCA'!$C$9:$C$564,$C15,'Dados DCA'!$E$9:$E$564,$D15,'Dados DCA'!$F$9:$F$564,"deducao_fundeb")=0,"",ABS(SUMIFS('Dados DCA'!$L$9:$L$564,'Dados DCA'!$C$9:$C$564,$C15,'Dados DCA'!$E$9:$E$564,$D15,'Dados DCA'!$F$9:$F$564,"deducao_fundeb"))) -> 16269559 | G15: =IF(COUNTIFS('Dados DCA'!$C$9:$C$564,$C15,'Dados DCA'!$E$9:$E$564,$D15,'Dados DCA'!$F$9:$F$564,"outras_deducoes")=0,"",ABS(SUMIFS('Dados DCA'!$L$9:$L$564,'Dados DCA'!$C$9:$C$564,$C15,'Dados DCA'!$E$9:$E$564,$D15,'Dados DCA'!$F$9:$F$564,"outras_deducoes"))) | H15: =IF(OR(E15="",F15=""),"",E15-F15-IF(G15="",0,G15)) -> 1.997464e+08 | I15: =IF(COUNTIFS('Dados DCA'!$C$9:$C$564,$C15,'Dados DCA'!$E$9:$E$564,$D15,'Dados DCA'!$F$9:$F$564,"despesa_empenhada_total")=0,"",SUMIFS('Dados DCA'!$L$9:$L$564,'Dados DCA'!$C$9:$C$564,$C15,'Dados DCA'!$E$9:$E$564,$D15,'Dados DCA'!$F$9:$F$564,"despesa_empenhada_total")) -> 1.9952192e+08 | J15: =IF(COUNTIFS('Dados DCA'!$C$9:$C$564,$C15,'Dados DCA'!$E$9:$E$564,$D15,'Dados DCA'!$F$9:$F$564,"despesa_liquidada_total")=0,"",SUMIFS('Dados DCA'!$L$9:$L$564,'Dados DCA'!$C$9:$C$564,$C15,'Dados DCA'!$E$9:$E$564,$D15,'Dados DCA'!$F$9:$F$564,"despesa_liquidada_total")) -> 1.963647e+08 | K15: =IF(COUNTIFS('Dados DCA'!$C$9:$C$564,$C15,'Dados DCA'!$E$9:$E$564,$D15,'Dados DCA'!$F$9:$F$564,"despesa_paga_total")=0,"",SUMIFS('Dados DCA'!$L$9:$L$564,'Dados DCA'!$C$9:$C$564,$C15,'Dados DCA'!$E$9:$E$564,$D15,'Dados DCA'!$F$9:$F$564,"despesa_paga_total")) -> 1.8955067e+08 | L15: =IF(COUNTIFS('Dados DCA'!$C$9:$C$564,$C15,'Dados DCA'!$E$9:$E$564,$D15,'Dados DCA'!$F$9:$F$564,"despesa_empenhada_exceto_intra")=0,"",SUMIFS('Dados DCA'!$L$9:$L$564,'Dados DCA'!$C$9:$C$564,$C15,'Dados DCA'!$E$9:$E$564,$D15,'Dados DCA'!$F$9:$F$564,"despesa_empenhada_exceto_intra")) -> 1.9108584e+08 | M15: =IF(OR(I15="",L15=""),"",I15-L15) -> 8436086.6 | N15: =IF(COUNTIFS('Dados DCA'!$C$9:$C$564,$C15,'Dados DCA'!$E$9:$E$564,$D15,'Dados DCA'!$F$9:$F$564,"receita_tributaria_propria_bruta")=0,"",SUMIFS('Dados DCA'!$L$9:$L$564,'Dados DCA'!$C$9:$C$564,$C15,'Dados DCA'!$E$9:$E$564,$D15,'Dados DCA'!$F$9:$F$564,"receita_tributaria_propria_bruta")) -> 24779690 | O15: =IF(COUNTIFS('Dados DCA'!$C$9:$C$564,$C15,'Dados DCA'!$E$9:$E$564,$D15,'Dados DCA'!$F$9:$F$564,"transferencias_correntes_total_brutas")=0,"",SUMIFS('Dados DCA'!$L$9:$L$564,'Dados DCA'!$C$9:$C$564,$C15,'Dados DCA'!$E$9:$E$564,$D15,'Dados DCA'!$F$9:$F$564,"transferencias_correntes_total_brutas")) -> 1.5738937e+08 | P15: =IF(COUNTIFS('Dados DCA'!$C$9:$C$564,$C15,'Dados DCA'!$E$9:$E$564,$D15,'Dados DCA'!$F$9:$F$564,"transferencias_intergov_correntes_proxy")=0,"",SUMIFS('Dados DCA'!$L$9:$L$564,'Dados DCA'!$C$9:$C$564,$C15,'Dados DCA'!$E$9:$E$564,$D15,'Dados DCA'!$F$9:$F$564,"transferencias_intergov_correntes_proxy")) -> 1.2131739e+08 | Q15: =IF(COUNTIFS('Dados IBGE'!$C$9:$C$164,$C15,'Dados IBGE'!$E$9:$E$164,$D15,'Dados IBGE'!$G$9:$G$164,"pop_censo")>0,SUMIFS('Dados IBGE'!$J$9:$J$164,'Dados IBGE'!$C$9:$C$164,$C15,'Dados IBGE'!$E$9:$E$164,$D15,'Dados IBGE'!$G$9:$G$164,"pop_censo"),IF(COUNTIFS('Dados IBGE'!$C$9:$C$164,$C15,'Dados IBGE'!$E$9:$E$164,$D15,'Dados IBGE'!$G$9:$G$164,"pop_estimada")=0,"",SUMIFS('Dados IBGE'!$J$9:$J$164,'Dados IBGE'!$C$9:$C$164,$C15,'Dados IBGE'!$E$9:$E$164,$D15,'Dados IBGE'!$G$9:$G$164,"pop_estimada"))) -> 75295 | R15: =IF(COUNTIFS('Dados IBGE'!$C$9:$C$164,$C15,'Dados IBGE'!$E$9:$E$164,$D15,'Dados IBGE'!$G$9:$G$164,"pib")=0,"",SUMIFS('Dados IBGE'!$J$9:$J$164,'Dados IBGE'!$C$9:$C$164,$C15,'Dados IBGE'!$E$9:$E$164,$D15,'Dados IBGE'!$G$9:$G$164,"pib")*1000) -> 1215383000 | S15: =IF(COUNTIFS('Dados IBGE'!$E$9:$E$164,$D15,'Dados IBGE'!$G$9:$G$164,"ipca")<>12,"",SUMIFS('Dados IBGE'!$J$9:$J$164,'Dados IBGE'!$E$9:$E$164,$D15,'Dados IBGE'!$G$9:$G$164,"ipca")/12) -> 5827.78 | T15: =IF(OR(S15="",S15=0),"",AVERAGEIFS('Dados IBGE'!$J$9:$J$164,'Dados IBGE'!$E$9:$E$164,2024,'Dados IBGE'!$G$9:$G$164,"ipca")/S15) -> 1.1929197 | U15: =IF(OR(E15="",T15=""),"",E15*T15) -> 2.5768969e+08 | V15: =IF(OR(I15="",T15=""),"",I15*T15) -> 2.3801362e+08 | W15: =IF(OR(Q15="",Q15=0,U15=""),"",U15/Q15) -> 3422.401 | X15: =IF(OR(Q15="",Q15=0,V15=""),"",V15/Q15) -> 3161.0814 | Y15: =IF(OR(E15="",E15=0,N15=""),"",N15/E15) -> 0.11471231 | Z15: =IF(OR(E15="",E15=0,O15=""),"",O15/E15) -> 0.72860063 | AA15: =IF(OR(R15="",R15=0,E15=""),"",E15/R15) -> 0.17773489 | AB15: =IF(OR(R15="",R15=0,I15=""),"",I15/R15) -> 0.16416383 | AC15: =IF(COUNTIFS('Dados DCA'!$C$9:$C$564,$C15,'Dados DCA'!$E$9:$E$564,$D15,'Dados DCA'!$F$9:$F$564,"receita_exceto_intra_bruta")=0,"",SUMIFS('Dados DCA'!$L$9:$L$564,'Dados DCA'!$C$9:$C$564,$C15,'Dados DCA'!$E$9:$E$564,$D15,'Dados DCA'!$F$9:$F$564,"receita_exceto_intra_bruta")) -> 2.0769956e+08 | AD15: =IF(COUNTIFS('Dados DCA'!$C$9:$C$564,$C15,'Dados DCA'!$E$9:$E$564,$D15,'Dados DCA'!$F$9:$F$564,"receita_intra_bruta")=0,"",SUMIFS('Dados DCA'!$L$9:$L$564,'Dados DCA'!$C$9:$C$564,$C15,'Dados DCA'!$E$9:$E$564,$D15,'Dados DCA'!$F$9:$F$564,"receita_intra_bruta")) -> 8316399.4
C16: Arcoverde/PE | D16: 2022 | E16: =IF(COUNTIFS('Dados DCA'!$C$9:$C$564,$C16,'Dados DCA'!$E$9:$E$564,$D16,'Dados DCA'!$F$9:$F$564,"receita_total_bruta")=0,"",SUMIFS('Dados DCA'!$L$9:$L$564,'Dados DCA'!$C$9:$C$564,$C16,'Dados DCA'!$E$9:$E$564,$D16,'Dados DCA'!$F$9:$F$564,"receita_total_bruta")) -> 2.583856e+08 | F16: =IF(COUNTIFS('Dados DCA'!$C$9:$C$564,$C16,'Dados DCA'!$E$9:$E$564,$D16,'Dados DCA'!$F$9:$F$564,"deducao_fundeb")=0,"",ABS(SUMIFS('Dados DCA'!$L$9:$L$564,'Dados DCA'!$C$9:$C$564,$C16,'Dados DCA'!$E$9:$E$564,$D16,'Dados DCA'!$F$9:$F$564,"deducao_fundeb"))) -> 19049129 | G16: =IF(COUNTIFS('Dados DCA'!$C$9:$C$564,$C16,'Dados DCA'!$E$9:$E$564,$D16,'Dados DCA'!$F$9:$F$564,"outras_deducoes")=0,"",ABS(SUMIFS('Dados DCA'!$L$9:$L$564,'Dados DCA'!$C$9:$C$564,$C16,'Dados DCA'!$E$9:$E$564,$D16,'Dados DCA'!$F$9:$F$564,"outras_deducoes"))) -> 1294.17 | H16: =IF(OR(E16="",F16=""),"",E16-F16-IF(G16="",0,G16)) -> 2.3933517e+08 | I16: =IF(COUNTIFS('Dados DCA'!$C$9:$C$564,$C16,'Dados DCA'!$E$9:$E$564,$D16,'Dados DCA'!$F$9:$F$564,"despesa_empenhada_total")=0,"",SUMIFS('Dados DCA'!$L$9:$L$564,'Dados DCA'!$C$9:$C$564,$C16,'Dados DCA'!$E$9:$E$564,$D16,'Dados DCA'!$F$9:$F$564,"despesa_empenhada_total")) -> 2.3805773e+08 | J16: =IF(COUNTIFS('Dados DCA'!$C$9:$C$564,$C16,'Dados DCA'!$E$9:$E$564,$D16,'Dados DCA'!$F$9:$F$564,"despesa_liquidada_total")=0,"",SUMIFS('Dados DCA'!$L$9:$L$564,'Dados DCA'!$C$9:$C$564,$C16,'Dados DCA'!$E$9:$E$564,$D16,'Dados DCA'!$F$9:$F$564,"despesa_liquidada_total")) -> 2.3805773e+08 | K16: =IF(COUNTIFS('Dados DCA'!$C$9:$C$564,$C16,'Dados DCA'!$E$9:$E$564,$D16,'Dados DCA'!$F$9:$F$564,"despesa_paga_total")=0,"",SUMIFS('Dados DCA'!$L$9:$L$564,'Dados DCA'!$C$9:$C$564,$C16,'Dados DCA'!$E$9:$E$564,$D16,'Dados DCA'!$F$9:$F$564,"despesa_paga_total")) -> 2.3089014e+08 | L16: =IF(COUNTIFS('Dados DCA'!$C$9:$C$564,$C16,'Dados DCA'!$E$9:$E$564,$D16,'Dados DCA'!$F$9:$F$564,"despesa_empenhada_exceto_intra")=0,"",SUMIFS('Dados DCA'!$L$9:$L$564,'Dados DCA'!$C$9:$C$564,$C16,'Dados DCA'!$E$9:$E$564,$D16,'Dados DCA'!$F$9:$F$564,"despesa_empenhada_exceto_intra")) -> 2.2742642e+08 | M16: =IF(OR(I16="",L16=""),"",I16-L16) -> 10631310 | N16: =IF(COUNTIFS('Dados DCA'!$C$9:$C$564,$C16,'Dados DCA'!$E$9:$E$564,$D16,'Dados DCA'!$F$9:$F$564,"receita_tributaria_propria_bruta")=0,"",SUMIFS('Dados DCA'!$L$9:$L$564,'Dados DCA'!$C$9:$C$564,$C16,'Dados DCA'!$E$9:$E$564,$D16,'Dados DCA'!$F$9:$F$564,"receita_tributaria_propria_bruta")) -> 27354131 | O16: =IF(COUNTIFS('Dados DCA'!$C$9:$C$564,$C16,'Dados DCA'!$E$9:$E$564,$D16,'Dados DCA'!$F$9:$F$564,"transferencias_correntes_total_brutas")=0,"",SUMIFS('Dados DCA'!$L$9:$L$564,'Dados DCA'!$C$9:$C$564,$C16,'Dados DCA'!$E$9:$E$564,$D16,'Dados DCA'!$F$9:$F$564,"transferencias_correntes_total_brutas")) -> 1.8661082e+08 | P16: =IF(COUNTIFS('Dados DCA'!$C$9:$C$564,$C16,'Dados DCA'!$E$9:$E$564,$D16,'Dados DCA'!$F$9:$F$564,"transferencias_intergov_correntes_proxy")=0,"",SUMIFS('Dados DCA'!$L$9:$L$564,'Dados DCA'!$C$9:$C$564,$C16,'Dados DCA'!$E$9:$E$564,$D16,'Dados DCA'!$F$9:$F$564,"transferencias_intergov_correntes_proxy")) -> 1.4797193e+08 | Q16: =IF(COUNTIFS('Dados IBGE'!$C$9:$C$164,$C16,'Dados IBGE'!$E$9:$E$164,$D16,'Dados IBGE'!$G$9:$G$164,"pop_censo")>0,SUMIFS('Dados IBGE'!$J$9:$J$164,'Dados IBGE'!$C$9:$C$164,$C16,'Dados IBGE'!$E$9:$E$164,$D16,'Dados IBGE'!$G$9:$G$164,"pop_censo"),IF(COUNTIFS('Dados IBGE'!$C$9:$C$164,$C16,'Dados IBGE'!$E$9:$E$164,$D16,'Dados IBGE'!$G$9:$G$164,"pop_estimada")=0,"",SUMIFS('Dados IBGE'!$J$9:$J$164,'Dados IBGE'!$C$9:$C$164,$C16,'Dados IBGE'!$E$9:$E$164,$D16,'Dados IBGE'!$G$9:$G$164,"pop_estimada"))) -> 77742 | R16: =IF(COUNTIFS('Dados IBGE'!$C$9:$C$164,$C16,'Dados IBGE'!$E$9:$E$164,$D16,'Dados IBGE'!$G$9:$G$164,"pib")=0,"",SUMIFS('Dados IBGE'!$J$9:$J$164,'Dados IBGE'!$C$9:$C$164,$C16,'Dados IBGE'!$E$9:$E$164,$D16,'Dados IBGE'!$G$9:$G$164,"pib")*1000) -> 1360082000 | S16: =IF(COUNTIFS('Dados IBGE'!$E$9:$E$164,$D16,'Dados IBGE'!$G$9:$G$164,"ipca")<>12,"",SUMIFS('Dados IBGE'!$J$9:$J$164,'Dados IBGE'!$E$9:$E$164,$D16,'Dados IBGE'!$G$9:$G$164,"ipca")/12) -> 6368.6042 | T16: =IF(OR(S16="",S16=0),"",AVERAGEIFS('Dados IBGE'!$J$9:$J$164,'Dados IBGE'!$E$9:$E$164,2024,'Dados IBGE'!$G$9:$G$164,"ipca")/S16) -> 1.0916165 | U16: =IF(OR(E16="",T16=""),"",E16*T16) -> 2.8205798e+08 | V16: =IF(OR(I16="",T16=""),"",I16*T16) -> 2.5986774e+08 | W16: =IF(OR(Q16="",Q16=0,U16=""),"",U16/Q16) -> 3628.1286 | X16: =IF(OR(Q16="",Q16=0,V16=""),"",V16/Q16) -> 3342.6943 | Y16: =IF(OR(E16="",E16=0,N16=""),"",N16/E16) -> 0.10586554 | Z16: =IF(OR(E16="",E16=0,O16=""),"",O16/E16) -> 0.72221837 | AA16: =IF(OR(R16="",R16=0,E16=""),"",E16/R16) -> 0.18997795 | AB16: =IF(OR(R16="",R16=0,I16=""),"",I16/R16) -> 0.17503189 | AC16: =IF(COUNTIFS('Dados DCA'!$C$9:$C$564,$C16,'Dados DCA'!$E$9:$E$564,$D16,'Dados DCA'!$F$9:$F$564,"receita_exceto_intra_bruta")=0,"",SUMIFS('Dados DCA'!$L$9:$L$564,'Dados DCA'!$C$9:$C$564,$C16,'Dados DCA'!$E$9:$E$564,$D16,'Dados DCA'!$F$9:$F$564,"receita_exceto_intra_bruta")) -> 2.4795132e+08 | AD16: =IF(COUNTIFS('Dados DCA'!$C$9:$C$564,$C16,'Dados DCA'!$E$9:$E$564,$D16,'Dados DCA'!$F$9:$F$564,"receita_intra_bruta")=0,"",SUMIFS('Dados DCA'!$L$9:$L$564,'Dados DCA'!$C$9:$C$564,$C16,'Dados DCA'!$E$9:$E$564,$D16,'Dados DCA'!$F$9:$F$564,"receita_intra_bruta")) -> 10434271
C17: Arcoverde/PE | D17: 2023 | E17: =IF(COUNTIFS('Dados DCA'!$C$9:$C$564,$C17,'Dados DCA'!$E$9:$E$564,$D17,'Dados DCA'!$F$9:$F$564,"receita_total_bruta")=0,"",SUMIFS('Dados DCA'!$L$9:$L$564,'Dados DCA'!$C$9:$C$564,$C17,'Dados DCA'!$E$9:$E$564,$D17,'Dados DCA'!$F$9:$F$564,"receita_total_bruta")) -> 2.8060635e+08 | F17: =IF(COUNTIFS('Dados DCA'!$C$9:$C$564,$C17,'Dados DCA'!$E$9:$E$564,$D17,'Dados DCA'!$F$9:$F$564,"deducao_fundeb")=0,"",ABS(SUMIFS('Dados DCA'!$L$9:$L$564,'Dados DCA'!$C$9:$C$564,$C17,'Dados DCA'!$E$9:$E$564,$D17,'Dados DCA'!$F$9:$F$564,"deducao_fundeb"))) -> 19179796 | G17: =IF(COUNTIFS('Dados DCA'!$C$9:$C$564,$C17,'Dados DCA'!$E$9:$E$564,$D17,'Dados DCA'!$F$9:$F$564,"outras_deducoes")=0,"",ABS(SUMIFS('Dados DCA'!$L$9:$L$564,'Dados DCA'!$C$9:$C$564,$C17,'Dados DCA'!$E$9:$E$564,$D17,'Dados DCA'!$F$9:$F$564,"outras_deducoes"))) -> 795879.78 | H17: =IF(OR(E17="",F17=""),"",E17-F17-IF(G17="",0,G17)) -> 2.6063067e+08 | I17: =IF(COUNTIFS('Dados DCA'!$C$9:$C$564,$C17,'Dados DCA'!$E$9:$E$564,$D17,'Dados DCA'!$F$9:$F$564,"despesa_empenhada_total")=0,"",SUMIFS('Dados DCA'!$L$9:$L$564,'Dados DCA'!$C$9:$C$564,$C17,'Dados DCA'!$E$9:$E$564,$D17,'Dados DCA'!$F$9:$F$564,"despesa_empenhada_total")) -> 2.6946922e+08 | J17: =IF(COUNTIFS('Dados DCA'!$C$9:$C$564,$C17,'Dados DCA'!$E$9:$E$564,$D17,'Dados DCA'!$F$9:$F$564,"despesa_liquidada_total")=0,"",SUMIFS('Dados DCA'!$L$9:$L$564,'Dados DCA'!$C$9:$C$564,$C17,'Dados DCA'!$E$9:$E$564,$D17,'Dados DCA'!$F$9:$F$564,"despesa_liquidada_total")) -> 2.6946922e+08 | K17: =IF(COUNTIFS('Dados DCA'!$C$9:$C$564,$C17,'Dados DCA'!$E$9:$E$564,$D17,'Dados DCA'!$F$9:$F$564,"despesa_paga_total")=0,"",SUMIFS('Dados DCA'!$L$9:$L$564,'Dados DCA'!$C$9:$C$564,$C17,'Dados DCA'!$E$9:$E$564,$D17,'Dados DCA'!$F$9:$F$564,"despesa_paga_total")) -> 2.6189212e+08 | L17: =IF(COUNTIFS('Dados DCA'!$C$9:$C$564,$C17,'Dados DCA'!$E$9:$E$564,$D17,'Dados DCA'!$F$9:$F$564,"despesa_empenhada_exceto_intra")=0,"",SUMIFS('Dados DCA'!$L$9:$L$564,'Dados DCA'!$C$9:$C$564,$C17,'Dados DCA'!$E$9:$E$564,$D17,'Dados DCA'!$F$9:$F$564,"despesa_empenhada_exceto_intra")) -> 2.5920749e+08 | M17: =IF(OR(I17="",L17=""),"",I17-L17) -> 10261731 | N17: =IF(COUNTIFS('Dados DCA'!$C$9:$C$564,$C17,'Dados DCA'!$E$9:$E$564,$D17,'Dados DCA'!$F$9:$F$564,"receita_tributaria_propria_bruta")=0,"",SUMIFS('Dados DCA'!$L$9:$L$564,'Dados DCA'!$C$9:$C$564,$C17,'Dados DCA'!$E$9:$E$564,$D17,'Dados DCA'!$F$9:$F$564,"receita_tributaria_propria_bruta")) -> 29430464 | O17: =IF(COUNTIFS('Dados DCA'!$C$9:$C$564,$C17,'Dados DCA'!$E$9:$E$564,$D17,'Dados DCA'!$F$9:$F$564,"transferencias_correntes_total_brutas")=0,"",SUMIFS('Dados DCA'!$L$9:$L$564,'Dados DCA'!$C$9:$C$564,$C17,'Dados DCA'!$E$9:$E$564,$D17,'Dados DCA'!$F$9:$F$564,"transferencias_correntes_total_brutas")) -> 1.9938523e+08 | P17: =IF(COUNTIFS('Dados DCA'!$C$9:$C$564,$C17,'Dados DCA'!$E$9:$E$564,$D17,'Dados DCA'!$F$9:$F$564,"transferencias_intergov_correntes_proxy")=0,"",SUMIFS('Dados DCA'!$L$9:$L$564,'Dados DCA'!$C$9:$C$564,$C17,'Dados DCA'!$E$9:$E$564,$D17,'Dados DCA'!$F$9:$F$564,"transferencias_intergov_correntes_proxy")) -> 1.5909127e+08 | Q17: =IF(COUNTIFS('Dados IBGE'!$C$9:$C$164,$C17,'Dados IBGE'!$E$9:$E$164,$D17,'Dados IBGE'!$G$9:$G$164,"pop_censo")>0,SUMIFS('Dados IBGE'!$J$9:$J$164,'Dados IBGE'!$C$9:$C$164,$C17,'Dados IBGE'!$E$9:$E$164,$D17,'Dados IBGE'!$G$9:$G$164,"pop_censo"),IF(COUNTIFS('Dados IBGE'!$C$9:$C$164,$C17,'Dados IBGE'!$E$9:$E$164,$D17,'Dados IBGE'!$G$9:$G$164,"pop_estimada")=0,"",SUMIFS('Dados IBGE'!$J$9:$J$164,'Dados IBGE'!$C$9:$C$164,$C17,'Dados IBGE'!$E$9:$E$164,$D17,'Dados IBGE'!$G$9:$G$164,"pop_estimada"))) | R17: =IF(COUNTIFS('Dados IBGE'!$C$9:$C$164,$C17,'Dados IBGE'!$E$9:$E$164,$D17,'Dados IBGE'!$G$9:$G$164,"pib")=0,"",SUMIFS('Dados IBGE'!$J$9:$J$164,'Dados IBGE'!$C$9:$C$164,$C17,'Dados IBGE'!$E$9:$E$164,$D17,'Dados IBGE'!$G$9:$G$164,"pib")*1000) -> 1503621000 | S17: =IF(COUNTIFS('Dados IBGE'!$E$9:$E$164,$D17,'Dados IBGE'!$G$9:$G$164,"ipca")<>12,"",SUMIFS('Dados IBGE'!$J$9:$J$164,'Dados IBGE'!$E$9:$E$164,$D17,'Dados IBGE'!$G$9:$G$164,"ipca")/12) -> 6661.15 | T17: =IF(OR(S17="",S17=0),"",AVERAGEIFS('Dados IBGE'!$J$9:$J$164,'Dados IBGE'!$E$9:$E$164,2024,'Dados IBGE'!$G$9:$G$164,"ipca")/S17) -> 1.0436746 | U17: =IF(OR(E17="",T17=""),"",E17*T17) -> 2.9286173e+08 | V17: =IF(OR(I17="",T17=""),"",I17*T17) -> 2.812382e+08 | W17: =IF(OR(Q17="",Q17=0,U17=""),"",U17/Q17) | X17: =IF(OR(Q17="",Q17=0,V17=""),"",V17/Q17) | Y17: =IF(OR(E17="",E17=0,N17=""),"",N17/E17) -> 0.10488168 | Z17: =IF(OR(E17="",E17=0,O17=""),"",O17/E17) -> 0.71055138 | AA17: =IF(OR(R17="",R17=0,E17=""),"",E17/R17) -> 0.1866204 | AB17: =IF(OR(R17="",R17=0,I17=""),"",I17/R17) -> 0.17921353 | AC17: =IF(COUNTIFS('Dados DCA'!$C$9:$C$564,$C17,'Dados DCA'!$E$9:$E$564,$D17,'Dados DCA'!$F$9:$F$564,"receita_exceto_intra_bruta")=0,"",SUMIFS('Dados DCA'!$L$9:$L$564,'Dados DCA'!$C$9:$C$564,$C17,'Dados DCA'!$E$9:$E$564,$D17,'Dados DCA'!$F$9:$F$564,"receita_exceto_intra_bruta")) -> 2.7084396e+08 | AD17: =IF(COUNTIFS('Dados DCA'!$C$9:$C$564,$C17,'Dados DCA'!$E$9:$E$564,$D17,'Dados DCA'!$F$9:$F$564,"receita_intra_bruta")=0,"",SUMIFS('Dados DCA'!$L$9:$L$564,'Dados DCA'!$C$9:$C$564,$C17,'Dados DCA'!$E$9:$E$564,$D17,'Dados DCA'!$F$9:$F$564,"receita_intra_bruta")) -> 9762381.4
C18: Arcoverde/PE | D18: 2024 | E18: =IF(COUNTIFS('Dados DCA'!$C$9:$C$564,$C18,'Dados DCA'!$E$9:$E$564,$D18,'Dados DCA'!$F$9:$F$564,"receita_total_bruta")=0,"",SUMIFS('Dados DCA'!$L$9:$L$564,'Dados DCA'!$C$9:$C$564,$C18,'Dados DCA'!$E$9:$E$564,$D18,'Dados DCA'!$F$9:$F$564,"receita_total_bruta")) -> 3.3882565e+08 | F18: =IF(COUNTIFS('Dados DCA'!$C$9:$C$564,$C18,'Dados DCA'!$E$9:$E$564,$D18,'Dados DCA'!$F$9:$F$564,"deducao_fundeb")=0,"",ABS(SUMIFS('Dados DCA'!$L$9:$L$564,'Dados DCA'!$C$9:$C$564,$C18,'Dados DCA'!$E$9:$E$564,$D18,'Dados DCA'!$F$9:$F$564,"deducao_fundeb"))) -> 21887725 | G18: =IF(COUNTIFS('Dados DCA'!$C$9:$C$564,$C18,'Dados DCA'!$E$9:$E$564,$D18,'Dados DCA'!$F$9:$F$564,"outras_deducoes")=0,"",ABS(SUMIFS('Dados DCA'!$L$9:$L$564,'Dados DCA'!$C$9:$C$564,$C18,'Dados DCA'!$E$9:$E$564,$D18,'Dados DCA'!$F$9:$F$564,"outras_deducoes"))) -> 27457.17 | H18: =IF(OR(E18="",F18=""),"",E18-F18-IF(G18="",0,G18)) -> 3.1691047e+08 | I18: =IF(COUNTIFS('Dados DCA'!$C$9:$C$564,$C18,'Dados DCA'!$E$9:$E$564,$D18,'Dados DCA'!$F$9:$F$564,"despesa_empenhada_total")=0,"",SUMIFS('Dados DCA'!$L$9:$L$564,'Dados DCA'!$C$9:$C$564,$C18,'Dados DCA'!$E$9:$E$564,$D18,'Dados DCA'!$F$9:$F$564,"despesa_empenhada_total")) -> 3.1725955e+08 | J18: =IF(COUNTIFS('Dados DCA'!$C$9:$C$564,$C18,'Dados DCA'!$E$9:$E$564,$D18,'Dados DCA'!$F$9:$F$564,"despesa_liquidada_total")=0,"",SUMIFS('Dados DCA'!$L$9:$L$564,'Dados DCA'!$C$9:$C$564,$C18,'Dados DCA'!$E$9:$E$564,$D18,'Dados DCA'!$F$9:$F$564,"despesa_liquidada_total")) -> 3.1725497e+08 | K18: =IF(COUNTIFS('Dados DCA'!$C$9:$C$564,$C18,'Dados DCA'!$E$9:$E$564,$D18,'Dados DCA'!$F$9:$F$564,"despesa_paga_total")=0,"",SUMIFS('Dados DCA'!$L$9:$L$564,'Dados DCA'!$C$9:$C$564,$C18,'Dados DCA'!$E$9:$E$564,$D18,'Dados DCA'!$F$9:$F$564,"despesa_paga_total")) -> 3.0580833e+08 | L18: =IF(COUNTIFS('Dados DCA'!$C$9:$C$564,$C18,'Dados DCA'!$E$9:$E$564,$D18,'Dados DCA'!$F$9:$F$564,"despesa_empenhada_exceto_intra")=0,"",SUMIFS('Dados DCA'!$L$9:$L$564,'Dados DCA'!$C$9:$C$564,$C18,'Dados DCA'!$E$9:$E$564,$D18,'Dados DCA'!$F$9:$F$564,"despesa_empenhada_exceto_intra")) -> 3.0665481e+08 | M18: =IF(OR(I18="",L18=""),"",I18-L18) -> 10604740 | N18: =IF(COUNTIFS('Dados DCA'!$C$9:$C$564,$C18,'Dados DCA'!$E$9:$E$564,$D18,'Dados DCA'!$F$9:$F$564,"receita_tributaria_propria_bruta")=0,"",SUMIFS('Dados DCA'!$L$9:$L$564,'Dados DCA'!$C$9:$C$564,$C18,'Dados DCA'!$E$9:$E$564,$D18,'Dados DCA'!$F$9:$F$564,"receita_tributaria_propria_bruta")) -> 34865349 | O18: =IF(COUNTIFS('Dados DCA'!$C$9:$C$564,$C18,'Dados DCA'!$E$9:$E$564,$D18,'Dados DCA'!$F$9:$F$564,"transferencias_correntes_total_brutas")=0,"",SUMIFS('Dados DCA'!$L$9:$L$564,'Dados DCA'!$C$9:$C$564,$C18,'Dados DCA'!$E$9:$E$564,$D18,'Dados DCA'!$F$9:$F$564,"transferencias_correntes_total_brutas")) -> 2.5413591e+08 | P18: =IF(COUNTIFS('Dados DCA'!$C$9:$C$564,$C18,'Dados DCA'!$E$9:$E$564,$D18,'Dados DCA'!$F$9:$F$564,"transferencias_intergov_correntes_proxy")=0,"",SUMIFS('Dados DCA'!$L$9:$L$564,'Dados DCA'!$C$9:$C$564,$C18,'Dados DCA'!$E$9:$E$564,$D18,'Dados DCA'!$F$9:$F$564,"transferencias_intergov_correntes_proxy")) -> 2.0599676e+08 | Q18: =IF(COUNTIFS('Dados IBGE'!$C$9:$C$164,$C18,'Dados IBGE'!$E$9:$E$164,$D18,'Dados IBGE'!$G$9:$G$164,"pop_censo")>0,SUMIFS('Dados IBGE'!$J$9:$J$164,'Dados IBGE'!$C$9:$C$164,$C18,'Dados IBGE'!$E$9:$E$164,$D18,'Dados IBGE'!$G$9:$G$164,"pop_censo"),IF(COUNTIFS('Dados IBGE'!$C$9:$C$164,$C18,'Dados IBGE'!$E$9:$E$164,$D18,'Dados IBGE'!$G$9:$G$164,"pop_estimada")=0,"",SUMIFS('Dados IBGE'!$J$9:$J$164,'Dados IBGE'!$C$9:$C$164,$C18,'Dados IBGE'!$E$9:$E$164,$D18,'Dados IBGE'!$G$9:$G$164,"pop_estimada"))) -> 82003 | R18: =IF(COUNTIFS('Dados IBGE'!$C$9:$C$164,$C18,'Dados IBGE'!$E$9:$E$164,$D18,'Dados IBGE'!$G$9:$G$164,"pib")=0,"",SUMIFS('Dados IBGE'!$J$9:$J$164,'Dados IBGE'!$C$9:$C$164,$C18,'Dados IBGE'!$E$9:$E$164,$D18,'Dados IBGE'!$G$9:$G$164,"pib")*1000) | S18: =IF(COUNTIFS('Dados IBGE'!$E$9:$E$164,$D18,'Dados IBGE'!$G$9:$G$164,"ipca")<>12,"",SUMIFS('Dados IBGE'!$J$9:$J$164,'Dados IBGE'!$E$9:$E$164,$D18,'Dados IBGE'!$G$9:$G$164,"ipca")/12) -> 6952.0733 | T18: =IF(OR(S18="",S18=0),"",AVERAGEIFS('Dados IBGE'!$J$9:$J$164,'Dados IBGE'!$E$9:$E$164,2024,'Dados IBGE'!$G$9:$G$164,"ipca")/S18) -> 1 | U18: =IF(OR(E18="",T18=""),"",E18*T18) -> 3.3882565e+08 | V18: =IF(OR(I18="",T18=""),"",I18*T18) -> 3.1725955e+08 | W18: =IF(OR(Q18="",Q18=0,U18=""),"",U18/Q18) -> 4131.8689 | X18: =IF(OR(Q18="",Q18=0,V18=""),"",V18/Q18) -> 3868.8774 | Y18: =IF(OR(E18="",E18=0,N18=""),"",N18/E18) -> 0.10290056 | Z18: =IF(OR(E18="",E18=0,O18=""),"",O18/E18) -> 0.7500492 | AA18: =IF(OR(R18="",R18=0,E18=""),"",E18/R18) | AB18: =IF(OR(R18="",R18=0,I18=""),"",I18/R18) | AC18: =IF(COUNTIFS('Dados DCA'!$C$9:$C$564,$C18,'Dados DCA'!$E$9:$E$564,$D18,'Dados DCA'!$F$9:$F$564,"receita_exceto_intra_bruta")=0,"",SUMIFS('Dados DCA'!$L$9:$L$564,'Dados DCA'!$C$9:$C$564,$C18,'Dados DCA'!$E$9:$E$564,$D18,'Dados DCA'!$F$9:$F$564,"receita_exceto_intra_bruta")) -> 327484071 | AD18: =IF(COUNTIFS('Dados DCA'!$C$9:$C$564,$C18,'Dados DCA'!$E$9:$E$564,$D18,'Dados DCA'!$F$9:$F$564,"receita_intra_bruta")=0,"",SUMIFS('Dados DCA'!$L$9:$L$564,'Dados DCA'!$C$9:$C$564,$C18,'Dados DCA'!$E$9:$E$564,$D18,'Dados DCA'!$F$9:$F$564,"receita_intra_bruta")) -> 11341577
C19: Araripina/PE | D19: 2015 | E19: =IF(COUNTIFS('Dados DCA'!$C$9:$C$564,$C19,'Dados DCA'!$E$9:$E$564,$D19,'Dados DCA'!$F$9:$F$564,"receita_total_bruta")=0,"",SUMIFS('Dados DCA'!$L$9:$L$564,'Dados DCA'!$C$9:$C$564,$C19,'Dados DCA'!$E$9:$E$564,$D19,'Dados DCA'!$F$9:$F$564,"receita_total_bruta")) -> 149488959 | F19: =IF(COUNTIFS('Dados DCA'!$C$9:$C$564,$C19,'Dados DCA'!$E$9:$E$564,$D19,'Dados DCA'!$F$9:$F$564,"deducao_fundeb")=0,"",ABS(SUMIFS('Dados DCA'!$L$9:$L$564,'Dados DCA'!$C$9:$C$564,$C19,'Dados DCA'!$E$9:$E$564,$D19,'Dados DCA'!$F$9:$F$564,"deducao_fundeb"))) -> 10093010 | G19: =IF(COUNTIFS('Dados DCA'!$C$9:$C$564,$C19,'Dados DCA'!$E$9:$E$564,$D19,'Dados DCA'!$F$9:$F$564,"outras_deducoes")=0,"",ABS(SUMIFS('Dados DCA'!$L$9:$L$564,'Dados DCA'!$C$9:$C$564,$C19,'Dados DCA'!$E$9:$E$564,$D19,'Dados DCA'!$F$9:$F$564,"outras_deducoes"))) | H19: =IF(OR(E19="",F19=""),"",E19-F19-IF(G19="",0,G19)) -> 1.3939595e+08 | I19: =IF(COUNTIFS('Dados DCA'!$C$9:$C$564,$C19,'Dados DCA'!$E$9:$E$564,$D19,'Dados DCA'!$F$9:$F$564,"despesa_empenhada_total")=0,"",SUMIFS('Dados DCA'!$L$9:$L$564,'Dados DCA'!$C$9:$C$564,$C19,'Dados DCA'!$E$9:$E$564,$D19,'Dados DCA'!$F$9:$F$564,"despesa_empenhada_total")) -> 1.4085029e+08 | J19: =IF(COUNTIFS('Dados DCA'!$C$9:$C$564,$C19,'Dados DCA'!$E$9:$E$564,$D19,'Dados DCA'!$F$9:$F$564,"despesa_liquidada_total")=0,"",SUMIFS('Dados DCA'!$L$9:$L$564,'Dados DCA'!$C$9:$C$564,$C19,'Dados DCA'!$E$9:$E$564,$D19,'Dados DCA'!$F$9:$F$564,"despesa_liquidada_total")) -> 1.4066153e+08 | K19: =IF(COUNTIFS('Dados DCA'!$C$9:$C$564,$C19,'Dados DCA'!$E$9:$E$564,$D19,'Dados DCA'!$F$9:$F$564,"despesa_paga_total")=0,"",SUMIFS('Dados DCA'!$L$9:$L$564,'Dados DCA'!$C$9:$C$564,$C19,'Dados DCA'!$E$9:$E$564,$D19,'Dados DCA'!$F$9:$F$564,"despesa_paga_total")) -> 1.3558279e+08 | L19: =IF(COUNTIFS('Dados DCA'!$C$9:$C$564,$C19,'Dados DCA'!$E$9:$E$564,$D19,'Dados DCA'!$F$9:$F$564,"despesa_empenhada_exceto_intra")=0,"",SUMIFS('Dados DCA'!$L$9:$L$564,'Dados DCA'!$C$9:$C$564,$C19,'Dados DCA'!$E$9:$E$564,$D19,'Dados DCA'!$F$9:$F$564,"despesa_empenhada_exceto_intra")) | M19: =IF(OR(I19="",L19=""),"",I19-L19) | N19: =IF(COUNTIFS('Dados DCA'!$C$9:$C$564,$C19,'Dados DCA'!$E$9:$E$564,$D19,'Dados DCA'!$F$9:$F$564,"receita_tributaria_propria_bruta")=0,"",SUMIFS('Dados DCA'!$L$9:$L$564,'Dados DCA'!$C$9:$C$564,$C19,'Dados DCA'!$E$9:$E$564,$D19,'Dados DCA'!$F$9:$F$564,"receita_tributaria_propria_bruta")) -> 6953850.5 | O19: =IF(COUNTIFS('Dados DCA'!$C$9:$C$564,$C19,'Dados DCA'!$E$9:$E$564,$D19,'Dados DCA'!$F$9:$F$564,"transferencias_correntes_total_brutas")=0,"",SUMIFS('Dados DCA'!$L$9:$L$564,'Dados DCA'!$C$9:$C$564,$C19,'Dados DCA'!$E$9:$E$564,$D19,'Dados DCA'!$F$9:$F$564,"transferencias_correntes_total_brutas")) -> 1.1927996e+08 | P19: =IF(COUNTIFS('Dados DCA'!$C$9:$C$564,$C19,'Dados DCA'!$E$9:$E$564,$D19,'Dados DCA'!$F$9:$F$564,"transferencias_intergov_correntes_proxy")=0,"",SUMIFS('Dados DCA'!$L$9:$L$564,'Dados DCA'!$C$9:$C$564,$C19,'Dados DCA'!$E$9:$E$564,$D19,'Dados DCA'!$F$9:$F$564,"transferencias_intergov_correntes_proxy")) -> 1.1920818e+08 | Q19: =IF(COUNTIFS('Dados IBGE'!$C$9:$C$164,$C19,'Dados IBGE'!$E$9:$E$164,$D19,'Dados IBGE'!$G$9:$G$164,"pop_censo")>0,SUMIFS('Dados IBGE'!$J$9:$J$164,'Dados IBGE'!$C$9:$C$164,$C19,'Dados IBGE'!$E$9:$E$164,$D19,'Dados IBGE'!$G$9:$G$164,"pop_censo"),IF(COUNTIFS('Dados IBGE'!$C$9:$C$164,$C19,'Dados IBGE'!$E$9:$E$164,$D19,'Dados IBGE'!$G$9:$G$164,"pop_estimada")=0,"",SUMIFS('Dados IBGE'!$J$9:$J$164,'Dados IBGE'!$C$9:$C$164,$C19,'Dados IBGE'!$E$9:$E$164,$D19,'Dados IBGE'!$G$9:$G$164,"pop_estimada"))) -> 82800 | R19: =IF(COUNTIFS('Dados IBGE'!$C$9:$C$164,$C19,'Dados IBGE'!$E$9:$E$164,$D19,'Dados IBGE'!$G$9:$G$164,"pib")=0,"",SUMIFS('Dados IBGE'!$J$9:$J$164,'Dados IBGE'!$C$9:$C$164,$C19,'Dados IBGE'!$E$9:$E$164,$D19,'Dados IBGE'!$G$9:$G$164,"pib")*1000) -> 758157000 | S19: =IF(COUNTIFS('Dados IBGE'!$E$9:$E$164,$D19,'Dados IBGE'!$G$9:$G$164,"ipca")<>12,"",SUMIFS('Dados IBGE'!$J$9:$J$164,'Dados IBGE'!$E$9:$E$164,$D19,'Dados IBGE'!$G$9:$G$164,"ipca")/12) -> 4310.1192 | T19: =IF(OR(S19="",S19=0),"",AVERAGEIFS('Dados IBGE'!$J$9:$J$164,'Dados IBGE'!$E$9:$E$164,2024,'Dados IBGE'!$G$9:$G$164,"ipca")/S19) -> 1.6129655 | U19: =IF(OR(E19="",T19=""),"",E19*T19) -> 2.4112053e+08 | V19: =IF(OR(I19="",T19=""),"",I19*T19) -> 2.2718665e+08 | W19: =IF(OR(Q19="",Q19=0,U19=""),"",U19/Q19) -> 2912.0837 | X19: =IF(OR(Q19="",Q19=0,V19=""),"",V19/Q19) -> 2743.8001 | Y19: =IF(OR(E19="",E19=0,N19=""),"",N19/E19) -> 0.046517485 | Z19: =IF(OR(E19="",E19=0,O19=""),"",O19/E19) -> 0.79791816 | AA19: =IF(OR(R19="",R19=0,E19=""),"",E19/R19) -> 0.19717415 | AB19: =IF(OR(R19="",R19=0,I19=""),"",I19/R19) -> 0.18577984 | AC19: =IF(COUNTIFS('Dados DCA'!$C$9:$C$564,$C19,'Dados DCA'!$E$9:$E$564,$D19,'Dados DCA'!$F$9:$F$564,"receita_exceto_intra_bruta")=0,"",SUMIFS('Dados DCA'!$L$9:$L$564,'Dados DCA'!$C$9:$C$564,$C19,'Dados DCA'!$E$9:$E$564,$D19,'Dados DCA'!$F$9:$F$564,"receita_exceto_intra_bruta")) | AD19: =IF(COUNTIFS('Dados DCA'!$C$9:$C$564,$C19,'Dados DCA'!$E$9:$E$564,$D19,'Dados DCA'!$F$9:$F$564,"receita_intra_bruta")=0,"",SUMIFS('Dados DCA'!$L$9:$L$564,'Dados DCA'!$C$9:$C$564,$C19,'Dados DCA'!$E$9:$E$564,$D19,'Dados DCA'!$F$9:$F$564,"receita_intra_bruta"))
C20: Araripina/PE | D20: 2016 | E20: =IF(COUNTIFS('Dados DCA'!$C$9:$C$564,$C20,'Dados DCA'!$E$9:$E$564,$D20,'Dados DCA'!$F$9:$F$564,"receita_total_bruta")=0,"",SUMIFS('Dados DCA'!$L$9:$L$564,'Dados DCA'!$C$9:$C$564,$C20,'Dados DCA'!$E$9:$E$564,$D20,'Dados DCA'!$F$9:$F$564,"receita_total_bruta")) -> 1.5301057e+08 | F20: =IF(COUNTIFS('Dados DCA'!$C$9:$C$564,$C20,'Dados DCA'!$E$9:$E$564,$D20,'Dados DCA'!$F$9:$F$564,"deducao_fundeb")=0,"",ABS(SUMIFS('Dados DCA'!$L$9:$L$564,'Dados DCA'!$C$9:$C$564,$C20,'Dados DCA'!$E$9:$E$564,$D20,'Dados DCA'!$F$9:$F$564,"deducao_fundeb"))) -> 11321945 | G20: =IF(COUNTIFS('Dados DCA'!$C$9:$C$564,$C20,'Dados DCA'!$E$9:$E$564,$D20,'Dados DCA'!$F$9:$F$564,"outras_deducoes")=0,"",ABS(SUMIFS('Dados DCA'!$L$9:$L$564,'Dados DCA'!$C$9:$C$564,$C20,'Dados DCA'!$E$9:$E$564,$D20,'Dados DCA'!$F$9:$F$564,"outras_deducoes"))) | H20: =IF(OR(E20="",F20=""),"",E20-F20-IF(G20="",0,G20)) -> 1.4168863e+08 | I20: =IF(COUNTIFS('Dados DCA'!$C$9:$C$564,$C20,'Dados DCA'!$E$9:$E$564,$D20,'Dados DCA'!$F$9:$F$564,"despesa_empenhada_total")=0,"",SUMIFS('Dados DCA'!$L$9:$L$564,'Dados DCA'!$C$9:$C$564,$C20,'Dados DCA'!$E$9:$E$564,$D20,'Dados DCA'!$F$9:$F$564,"despesa_empenhada_total")) -> 1.4455995e+08 | J20: =IF(COUNTIFS('Dados DCA'!$C$9:$C$564,$C20,'Dados DCA'!$E$9:$E$564,$D20,'Dados DCA'!$F$9:$F$564,"despesa_liquidada_total")=0,"",SUMIFS('Dados DCA'!$L$9:$L$564,'Dados DCA'!$C$9:$C$564,$C20,'Dados DCA'!$E$9:$E$564,$D20,'Dados DCA'!$F$9:$F$564,"despesa_liquidada_total")) -> 1.4409522e+08 | K20: =IF(COUNTIFS('Dados DCA'!$C$9:$C$564,$C20,'Dados DCA'!$E$9:$E$564,$D20,'Dados DCA'!$F$9:$F$564,"despesa_paga_total")=0,"",SUMIFS('Dados DCA'!$L$9:$L$564,'Dados DCA'!$C$9:$C$564,$C20,'Dados DCA'!$E$9:$E$564,$D20,'Dados DCA'!$F$9:$F$564,"despesa_paga_total")) -> 1.3747398e+08 | L20: =IF(COUNTIFS('Dados DCA'!$C$9:$C$564,$C20,'Dados DCA'!$E$9:$E$564,$D20,'Dados DCA'!$F$9:$F$564,"despesa_empenhada_exceto_intra")=0,"",SUMIFS('Dados DCA'!$L$9:$L$564,'Dados DCA'!$C$9:$C$564,$C20,'Dados DCA'!$E$9:$E$564,$D20,'Dados DCA'!$F$9:$F$564,"despesa_empenhada_exceto_intra")) | M20: =IF(OR(I20="",L20=""),"",I20-L20) | N20: =IF(COUNTIFS('Dados DCA'!$C$9:$C$564,$C20,'Dados DCA'!$E$9:$E$564,$D20,'Dados DCA'!$F$9:$F$564,"receita_tributaria_propria_bruta")=0,"",SUMIFS('Dados DCA'!$L$9:$L$564,'Dados DCA'!$C$9:$C$564,$C20,'Dados DCA'!$E$9:$E$564,$D20,'Dados DCA'!$F$9:$F$564,"receita_tributaria_propria_bruta")) -> 8421767.3 | O20: =IF(COUNTIFS('Dados DCA'!$C$9:$C$564,$C20,'Dados DCA'!$E$9:$E$564,$D20,'Dados DCA'!$F$9:$F$564,"transferencias_correntes_total_brutas")=0,"",SUMIFS('Dados DCA'!$L$9:$L$564,'Dados DCA'!$C$9:$C$564,$C20,'Dados DCA'!$E$9:$E$564,$D20,'Dados DCA'!$F$9:$F$564,"transferencias_correntes_total_brutas")) -> 1.2219738e+08 | P20: =IF(COUNTIFS('Dados DCA'!$C$9:$C$564,$C20,'Dados DCA'!$E$9:$E$564,$D20,'Dados DCA'!$F$9:$F$564,"transferencias_intergov_correntes_proxy")=0,"",SUMIFS('Dados DCA'!$L$9:$L$564,'Dados DCA'!$C$9:$C$564,$C20,'Dados DCA'!$E$9:$E$564,$D20,'Dados DCA'!$F$9:$F$564,"transferencias_intergov_correntes_proxy")) -> 1.2208481e+08 | Q20: =IF(COUNTIFS('Dados IBGE'!$C$9:$C$164,$C20,'Dados IBGE'!$E$9:$E$164,$D20,'Dados IBGE'!$G$9:$G$164,"pop_censo")>0,SUMIFS('Dados IBGE'!$J$9:$J$164,'Dados IBGE'!$C$9:$C$164,$C20,'Dados IBGE'!$E$9:$E$164,$D20,'Dados IBGE'!$G$9:$G$164,"pop_censo"),IF(COUNTIFS('Dados IBGE'!$C$9:$C$164,$C20,'Dados IBGE'!$E$9:$E$164,$D20,'Dados IBGE'!$G$9:$G$164,"pop_estimada")=0,"",SUMIFS('Dados IBGE'!$J$9:$J$164,'Dados IBGE'!$C$9:$C$164,$C20,'Dados IBGE'!$E$9:$E$164,$D20,'Dados IBGE'!$G$9:$G$164,"pop_estimada"))) -> 83287 | R20: =IF(COUNTIFS('Dados IBGE'!$C$9:$C$164,$C20,'Dados IBGE'!$E$9:$E$164,$D20,'Dados IBGE'!$G$9:$G$164,"pib")=0,"",SUMIFS('Dados IBGE'!$J$9:$J$164,'Dados IBGE'!$C$9:$C$164,$C20,'Dados IBGE'!$E$9:$E$164,$D20,'Dados IBGE'!$G$9:$G$164,"pib")*1000) -> 786323000 | S20: =IF(COUNTIFS('Dados IBGE'!$E$9:$E$164,$D20,'Dados IBGE'!$G$9:$G$164,"ipca")<>12,"",SUMIFS('Dados IBGE'!$J$9:$J$164,'Dados IBGE'!$E$9:$E$164,$D20,'Dados IBGE'!$G$9:$G$164,"ipca")/12) -> 4686.7867 | T20: =IF(OR(S20="",S20=0),"",AVERAGEIFS('Dados IBGE'!$J$9:$J$164,'Dados IBGE'!$E$9:$E$164,2024,'Dados IBGE'!$G$9:$G$164,"ipca")/S20) -> 1.4833347 | U20: =IF(OR(E20="",T20=""),"",E20*T20) -> 2.2696589e+08 | V20: =IF(OR(I20="",T20=""),"",I20*T20) -> 2.1443079e+08 | W20: =IF(OR(Q20="",Q20=0,U20=""),"",U20/Q20) -> 2725.1059 | X20: =IF(OR(Q20="",Q20=0,V20=""),"",V20/Q20) -> 2574.601 | Y20: =IF(OR(E20="",E20=0,N20=""),"",N20/E20) -> 0.055040428 | Z20: =IF(OR(E20="",E20=0,O20=""),"",O20/E20) -> 0.79862052 | AA20: =IF(OR(R20="",R20=0,E20=""),"",E20/R20) -> 0.19458997 | AB20: =IF(OR(R20="",R20=0,I20=""),"",I20/R20) -> 0.18384296 | AC20: =IF(COUNTIFS('Dados DCA'!$C$9:$C$564,$C20,'Dados DCA'!$E$9:$E$564,$D20,'Dados DCA'!$F$9:$F$564,"receita_exceto_intra_bruta")=0,"",SUMIFS('Dados DCA'!$L$9:$L$564,'Dados DCA'!$C$9:$C$564,$C20,'Dados DCA'!$E$9:$E$564,$D20,'Dados DCA'!$F$9:$F$564,"receita_exceto_intra_bruta")) | AD20: =IF(COUNTIFS('Dados DCA'!$C$9:$C$564,$C20,'Dados DCA'!$E$9:$E$564,$D20,'Dados DCA'!$F$9:$F$564,"receita_intra_bruta")=0,"",SUMIFS('Dados DCA'!$L$9:$L$564,'Dados DCA'!$C$9:$C$564,$C20,'Dados DCA'!$E$9:$E$564,$D20,'Dados DCA'!$F$9:$F$564,"receita_intra_bruta"))
... C28: Araripina/PE | D28: 2024 | E28: =IF(COUNTIFS('Dados DCA'!$C$9:$C$564,$C28,'Dados DCA'!$E$9:$E$564,$D28,'Dados DCA'!$F$9:$F$564,"receita_total_bruta")=0,"",SUMIFS('Dados DCA'!$L$9:$L$564,'Dados DCA'!$C$9:$C$564,$C28,'Dados DCA'!$E$9:$E$564,$D28,'Dados DCA'!$F$9:$F$564,"receita_total_bruta")) -> 4.0675034e+08 | F28: =IF(COUNTIFS('Dados DCA'!$C$9:$C$564,$C28,'Dados DCA'!$E$9:$E$564,$D28,'Dados DCA'!$F$9:$F$564,"deducao_fundeb")=0,"",ABS(SUMIFS('Dados DCA'!$L$9:$L$564,'Dados DCA'!$C$9:$C$564,$C28,'Dados DCA'!$E$9:$E$564,$D28,'Dados DCA'!$F$9:$F$564,"deducao_fundeb"))) -> 23207682 | G28: =IF(COUNTIFS('Dados DCA'!$C$9:$C$564,$C28,'Dados DCA'!$E$9:$E$564,$D28,'Dados DCA'!$F$9:$F$564,"outras_deducoes")=0,"",ABS(SUMIFS('Dados DCA'!$L$9:$L$564,'Dados DCA'!$C$9:$C$564,$C28,'Dados DCA'!$E$9:$E$564,$D28,'Dados DCA'!$F$9:$F$564,"outras_deducoes"))) -> 227714.97 | H28: =IF(OR(E28="",F28=""),"",E28-F28-IF(G28="",0,G28)) -> 3.8331494e+08 | I28: =IF(COUNTIFS('Dados DCA'!$C$9:$C$564,$C28,'Dados DCA'!$E$9:$E$564,$D28,'Dados DCA'!$F$9:$F$564,"despesa_empenhada_total")=0,"",SUMIFS('Dados DCA'!$L$9:$L$564,'Dados DCA'!$C$9:$C$564,$C28,'Dados DCA'!$E$9:$E$564,$D28,'Dados DCA'!$F$9:$F$564,"despesa_empenhada_total")) -> 3.9993486e+08 | J28: =IF(COUNTIFS('Dados DCA'!$C$9:$C$564,$C28,'Dados DCA'!$E$9:$E$564,$D28,'Dados DCA'!$F$9:$F$564,"despesa_liquidada_total")=0,"",SUMIFS('Dados DCA'!$L$9:$L$564,'Dados DCA'!$C$9:$C$564,$C28,'Dados DCA'!$E$9:$E$564,$D28,'Dados DCA'!$F$9:$F$564,"despesa_liquidada_total")) -> 3.9993486e+08 | K28: =IF(COUNTIFS('Dados DCA'!$C$9:$C$564,$C28,'Dados DCA'!$E$9:$E$564,$D28,'Dados DCA'!$F$9:$F$564,"despesa_paga_total")=0,"",SUMIFS('Dados DCA'!$L$9:$L$564,'Dados DCA'!$C$9:$C$564,$C28,'Dados DCA'!$E$9:$E$564,$D28,'Dados DCA'!$F$9:$F$564,"despesa_paga_total")) -> 3.9550788e+08 | L28: =IF(COUNTIFS('Dados DCA'!$C$9:$C$564,$C28,'Dados DCA'!$E$9:$E$564,$D28,'Dados DCA'!$F$9:$F$564,"despesa_empenhada_exceto_intra")=0,"",SUMIFS('Dados DCA'!$L$9:$L$564,'Dados DCA'!$C$9:$C$564,$C28,'Dados DCA'!$E$9:$E$564,$D28,'Dados DCA'!$F$9:$F$564,"despesa_empenhada_exceto_intra")) -> 3.6822617e+08 | M28: =IF(OR(I28="",L28=""),"",I28-L28) -> 31708697 | N28: =IF(COUNTIFS('Dados DCA'!$C$9:$C$564,$C28,'Dados DCA'!$E$9:$E$564,$D28,'Dados DCA'!$F$9:$F$564,"receita_tributaria_propria_bruta")=0,"",SUMIFS('Dados DCA'!$L$9:$L$564,'Dados DCA'!$C$9:$C$564,$C28,'Dados DCA'!$E$9:$E$564,$D28,'Dados DCA'!$F$9:$F$564,"receita_tributaria_propria_bruta")) -> 26108587 | O28: =IF(COUNTIFS('Dados DCA'!$C$9:$C$564,$C28,'Dados DCA'!$E$9:$E$564,$D28,'Dados DCA'!$F$9:$F$564,"transferencias_correntes_total_brutas")=0,"",SUMIFS('Dados DCA'!$L$9:$L$564,'Dados DCA'!$C$9:$C$564,$C28,'Dados DCA'!$E$9:$E$564,$D28,'Dados DCA'!$F$9:$F$564,"transferencias_correntes_total_brutas")) -> 2.9880755e+08 | P28: =IF(COUNTIFS('Dados DCA'!$C$9:$C$564,$C28,'Dados DCA'!$E$9:$E$564,$D28,'Dados DCA'!$F$9:$F$564,"transferencias_intergov_correntes_proxy")=0,"",SUMIFS('Dados DCA'!$L$9:$L$564,'Dados DCA'!$C$9:$C$564,$C28,'Dados DCA'!$E$9:$E$564,$D28,'Dados DCA'!$F$9:$F$564,"transferencias_intergov_correntes_proxy")) -> 2.2307436e+08 | Q28: =IF(COUNTIFS('Dados IBGE'!$C$9:$C$164,$C28,'Dados IBGE'!$E$9:$E$164,$D28,'Dados IBGE'!$G$9:$G$164,"pop_censo")>0,SUMIFS('Dados IBGE'!$J$9:$J$164,'Dados IBGE'!$C$9:$C$164,$C28,'Dados IBGE'!$E$9:$E$164,$D28,'Dados IBGE'!$G$9:$G$164,"pop_censo"),IF(COUNTIFS('Dados IBGE'!$C$9:$C$164,$C28,'Dados IBGE'!$E$9:$E$164,$D28,'Dados IBGE'!$G$9:$G$164,"pop_estimada")=0,"",SUMIFS('Dados IBGE'!$J$9:$J$164,'Dados IBGE'!$C$9:$C$164,$C28,'Dados IBGE'!$E$9:$E$164,$D28,'Dados IBGE'!$G$9:$G$164,"pop_estimada"))) -> 90104 | R28: =IF(COUNTIFS('Dados IBGE'!$C$9:$C$164,$C28,'Dados IBGE'!$E$9:$E$164,$D28,'Dados IBGE'!$G$9:$G$164,"pib")=0,"",SUMIFS('Dados IBGE'!$J$9:$J$164,'Dados IBGE'!$C$9:$C$164,$C28,'Dados IBGE'!$E$9:$E$164,$D28,'Dados IBGE'!$G$9:$G$164,"pib")*1000) | S28: =IF(COUNTIFS('Dados IBGE'!$E$9:$E$164,$D28,'Dados IBGE'!$G$9:$G$164,"ipca")<>12,"",SUMIFS('Dados IBGE'!$J$9:$J$164,'Dados IBGE'!$E$9:$E$164,$D28,'Dados IBGE'!$G$9:$G$164,"ipca")/12) -> 6952.0733 | T28: =IF(OR(S28="",S28=0),"",AVERAGEIFS('Dados IBGE'!$J$9:$J$164,'Dados IBGE'!$E$9:$E$164,2024,'Dados IBGE'!$G$9:$G$164,"ipca")/S28) -> 1 | U28: =IF(OR(E28="",T28=""),"",E28*T28) -> 4.0675034e+08 | V28: =IF(OR(I28="",T28=""),"",I28*T28) -> 3.9993486e+08 | W28: =IF(OR(Q28="",Q28=0,U28=""),"",U28/Q28) -> 4514.2318 | X28: =IF(OR(Q28="",Q28=0,V28=""),"",V28/Q28) -> 4438.5917 | Y28: =IF(OR(E28="",E28=0,N28=""),"",N28/E28) -> 0.064188236 | Z28: =IF(OR(E28="",E28=0,O28=""),"",O28/E28) -> 0.73462152 | AA28: =IF(OR(R28="",R28=0,E28=""),"",E28/R28) | AB28: =IF(OR(R28="",R28=0,I28=""),"",I28/R28) | AC28: =IF(COUNTIFS('Dados DCA'!$C$9:$C$564,$C28,'Dados DCA'!$E$9:$E$564,$D28,'Dados DCA'!$F$9:$F$564,"receita_exceto_intra_bruta")=0,"",SUMIFS('Dados DCA'!$L$9:$L$564,'Dados DCA'!$C$9:$C$564,$C28,'Dados DCA'!$E$9:$E$564,$D28,'Dados DCA'!$F$9:$F$564,"receita_exceto_intra_bruta")) -> 3.7720255e+08 | AD28: =IF(COUNTIFS('Dados DCA'!$C$9:$C$564,$C28,'Dados DCA'!$E$9:$E$564,$D28,'Dados DCA'!$F$9:$F$564,"receita_intra_bruta")=0,"",SUMIFS('Dados DCA'!$L$9:$L$564,'Dados DCA'!$C$9:$C$564,$C28,'Dados DCA'!$E$9:$E$564,$D28,'Dados DCA'!$F$9:$F$564,"receita_intra_bruta")) -> 29547787

Sheet Funções
C3: Despesa empenhada por função
C5: Funções de primeiro nível; seleção sem soma simultânea de conta-pai e filhas.
C6: R$ correntes e R$ médios de 2024; participação sobre o total empenhado exceto intra.
C8: Município | D8: Ano | E8: Código da função | F8: Função | G8: Despesa empenhada exceto intra nominal | H8: Despesa em reais médios de 2024 | I8: Participação na despesa funcional | J8: Arquivo DCA
C9: Arcoverde/PE | D9: 2017 | E9: 01 | F9: Legislativa | G9: =IF(COUNTIFS('Dados DCA'!$C$9:$C$564,$C9,'Dados DCA'!$E$9:$E$564,$D9,'Dados DCA'!$F$9:$F$564,"despesa_funcao_"&$E9)=0,"",SUMIFS('Dados DCA'!$L$9:$L$564,'Dados DCA'!$C$9:$C$564,$C9,'Dados DCA'!$E$9:$E$564,$D9,'Dados DCA'!$F$9:$F$564,"despesa_funcao_"&$E9)) -> 5342557.3 | H9: =IF(OR(G9="",SUMIFS('Cálculos Municipais'!$T$9:$T$28,'Cálculos Municipais'!$C$9:$C$28,$C9,'Cálculos Municipais'!$D$9:$D$28,$D9)=0),"",G9*SUMIFS('Cálculos Municipais'!$T$9:$T$28,'Cálculos Municipais'!$C$9:$C$28,$C9,'Cálculos Municipais'!$D$9:$D$28,$D9)) -> 7660781.5 | I9: =IF(OR(G9="",SUMIFS('Dados DCA'!$L$9:$L$564,'Dados DCA'!$C$9:$C$564,$C9,'Dados DCA'!$E$9:$E$564,$D9,'Dados DCA'!$F$9:$F$564,"despesa_empenhada_exceto_intra")=0),"",G9/SUMIFS('Dados DCA'!$L$9:$L$564,'Dados DCA'!$C$9:$C$564,$C9,'Dados DCA'!$E$9:$E$564,$D9,'Dados DCA'!$F$9:$F$564,"despesa_empenhada_exceto_intra")) -> 0.040017255 | J9: siconfi_dca_arcoverde_2017.json
C10: Arcoverde/PE | D10: 2017 | E10: 04 | F10: Administração | G10: =IF(COUNTIFS('Dados DCA'!$C$9:$C$564,$C10,'Dados DCA'!$E$9:$E$564,$D10,'Dados DCA'!$F$9:$F$564,"despesa_funcao_"&$E10)=0,"",SUMIFS('Dados DCA'!$L$9:$L$564,'Dados DCA'!$C$9:$C$564,$C10,'Dados DCA'!$E$9:$E$564,$D10,'Dados DCA'!$F$9:$F$564,"despesa_funcao_"&$E10)) -> 26594984 | H10: =IF(OR(G10="",SUMIFS('Cálculos Municipais'!$T$9:$T$28,'Cálculos Municipais'!$C$9:$C$28,$C10,'Cálculos Municipais'!$D$9:$D$28,$D10)=0),"",G10*SUMIFS('Cálculos Municipais'!$T$9:$T$28,'Cálculos Municipais'!$C$9:$C$28,$C10,'Cálculos Municipais'!$D$9:$D$28,$D10)) -> 38134989 | I10: =IF(OR(G10="",SUMIFS('Dados DCA'!$L$9:$L$564,'Dados DCA'!$C$9:$C$564,$C10,'Dados DCA'!$E$9:$E$564,$D10,'Dados DCA'!$F$9:$F$564,"despesa_empenhada_exceto_intra")=0),"",G10/SUMIFS('Dados DCA'!$L$9:$L$564,'Dados DCA'!$C$9:$C$564,$C10,'Dados DCA'!$E$9:$E$564,$D10,'Dados DCA'!$F$9:$F$564,"despesa_empenhada_exceto_intra")) -> 0.1992039 | J10: siconfi_dca_arcoverde_2017.json
C11: Arcoverde/PE | D11: 2017 | E11: 08 | F11: Assistência Social | G11: =IF(COUNTIFS('Dados DCA'!$C$9:$C$564,$C11,'Dados DCA'!$E$9:$E$564,$D11,'Dados DCA'!$F$9:$F$564,"despesa_funcao_"&$E11)=0,"",SUMIFS('Dados DCA'!$L$9:$L$564,'Dados DCA'!$C$9:$C$564,$C11,'Dados DCA'!$E$9:$E$564,$D11,'Dados DCA'!$F$9:$F$564,"despesa_funcao_"&$E11)) -> 4219845.5 | H11: =IF(OR(G11="",SUMIFS('Cálculos Municipais'!$T$9:$T$28,'Cálculos Municipais'!$C$9:$C$28,$C11,'Cálculos Municipais'!$D$9:$D$28,$D11)=0),"",G11*SUMIFS('Cálculos Municipais'!$T$9:$T$28,'Cálculos Municipais'!$C$9:$C$28,$C11,'Cálculos Municipais'!$D$9:$D$28,$D11)) -> 6050906.4 | I11: =IF(OR(G11="",SUMIFS('Dados DCA'!$L$9:$L$564,'Dados DCA'!$C$9:$C$564,$C11,'Dados DCA'!$E$9:$E$564,$D11,'Dados DCA'!$F$9:$F$564,"despesa_empenhada_exceto_intra")=0),"",G11/SUMIFS('Dados DCA'!$L$9:$L$564,'Dados DCA'!$C$9:$C$564,$C11,'Dados DCA'!$E$9:$E$564,$D11,'Dados DCA'!$F$9:$F$564,"despesa_empenhada_exceto_intra")) -> 0.031607828 | J11: siconfi_dca_arcoverde_2017.json
C12: Arcoverde/PE | D12: 2017 | E12: 09 | F12: Previdência Social | G12: =IF(COUNTIFS('Dados DCA'!$C$9:$C$564,$C12,'Dados DCA'!$E$9:$E$564,$D12,'Dados DCA'!$F$9:$F$564,"despesa_funcao_"&$E12)=0,"",SUMIFS('Dados DCA'!$L$9:$L$564,'Dados DCA'!$C$9:$C$564,$C12,'Dados DCA'!$E$9:$E$564,$D12,'Dados DCA'!$F$9:$F$564,"despesa_funcao_"&$E12)) -> 14754364 | H12: =IF(OR(G12="",SUMIFS('Cálculos Municipais'!$T$9:$T$28,'Cálculos Municipais'!$C$9:$C$28,$C12,'Cálculos Municipais'!$D$9:$D$28,$D12)=0),"",G12*SUMIFS('Cálculos Municipais'!$T$9:$T$28,'Cálculos Municipais'!$C$9:$C$28,$C12,'Cálculos Municipais'!$D$9:$D$28,$D12)) -> 21156527 | I12: =IF(OR(G12="",SUMIFS('Dados DCA'!$L$9:$L$564,'Dados DCA'!$C$9:$C$564,$C12,'Dados DCA'!$E$9:$E$564,$D12,'Dados DCA'!$F$9:$F$564,"despesa_empenhada_exceto_intra")=0),"",G12/SUMIFS('Dados DCA'!$L$9:$L$564,'Dados DCA'!$C$9:$C$564,$C12,'Dados DCA'!$E$9:$E$564,$D12,'Dados DCA'!$F$9:$F$564,"despesa_empenhada_exceto_intra")) -> 0.11051433 | J12: siconfi_dca_arcoverde_2017.json
C13: Arcoverde/PE | D13: 2017 | E13: 10 | F13: Saúde | G13: =IF(COUNTIFS('Dados DCA'!$C$9:$C$564,$C13,'Dados DCA'!$E$9:$E$564,$D13,'Dados DCA'!$F$9:$F$564,"despesa_funcao_"&$E13)=0,"",SUMIFS('Dados DCA'!$L$9:$L$564,'Dados DCA'!$C$9:$C$564,$C13,'Dados DCA'!$E$9:$E$564,$D13,'Dados DCA'!$F$9:$F$564,"despesa_funcao_"&$E13)) -> 30659767 | H13: =IF(OR(G13="",SUMIFS('Cálculos Municipais'!$T$9:$T$28,'Cálculos Municipais'!$C$9:$C$28,$C13,'Cálculos Municipais'!$D$9:$D$28,$D13)=0),"",G13*SUMIFS('Cálculos Municipais'!$T$9:$T$28,'Cálculos Municipais'!$C$9:$C$28,$C13,'Cálculos Municipais'!$D$9:$D$28,$D13)) -> 43963548 | I13: =IF(OR(G13="",SUMIFS('Dados DCA'!$L$9:$L$564,'Dados DCA'!$C$9:$C$564,$C13,'Dados DCA'!$E$9:$E$564,$D13,'Dados DCA'!$F$9:$F$564,"despesa_empenhada_exceto_intra")=0),"",G13/SUMIFS('Dados DCA'!$L$9:$L$564,'Dados DCA'!$C$9:$C$564,$C13,'Dados DCA'!$E$9:$E$564,$D13,'Dados DCA'!$F$9:$F$564,"despesa_empenhada_exceto_intra")) -> 0.22965026 | J13: siconfi_dca_arcoverde_2017.json
C14: Arcoverde/PE | D14: 2017 | E14: 11 | F14: Trabalho | G14: =IF(COUNTIFS('Dados DCA'!$C$9:$C$564,$C14,'Dados DCA'!$E$9:$E$564,$D14,'Dados DCA'!$F$9:$F$564,"despesa_funcao_"&$E14)=0,"",SUMIFS('Dados DCA'!$L$9:$L$564,'Dados DCA'!$C$9:$C$564,$C14,'Dados DCA'!$E$9:$E$564,$D14,'Dados DCA'!$F$9:$F$564,"despesa_funcao_"&$E14)) -> 1022 | H14: =IF(OR(G14="",SUMIFS('Cálculos Municipais'!$T$9:$T$28,'Cálculos Municipais'!$C$9:$C$28,$C14,'Cálculos Municipais'!$D$9:$D$28,$D14)=0),"",G14*SUMIFS('Cálculos Municipais'!$T$9:$T$28,'Cálculos Municipais'!$C$9:$C$28,$C14,'Cálculos Municipais'!$D$9:$D$28,$D14)) -> 1465.4628 | I14: =IF(OR(G14="",SUMIFS('Dados DCA'!$L$9:$L$564,'Dados DCA'!$C$9:$C$564,$C14,'Dados DCA'!$E$9:$E$564,$D14,'Dados DCA'!$F$9:$F$564,"despesa_empenhada_exceto_intra")=0),"",G14/SUMIFS('Dados DCA'!$L$9:$L$564,'Dados DCA'!$C$9:$C$564,$C14,'Dados DCA'!$E$9:$E$564,$D14,'Dados DCA'!$F$9:$F$564,"despesa_empenhada_exceto_intra")) -> 7.6550671e-06 | J14: siconfi_dca_arcoverde_2017.json
C15: Arcoverde/PE | D15: 2017 | E15: 12 | F15: Educação | G15: =IF(COUNTIFS('Dados DCA'!$C$9:$C$564,$C15,'Dados DCA'!$E$9:$E$564,$D15,'Dados DCA'!$F$9:$F$564,"despesa_funcao_"&$E15)=0,"",SUMIFS('Dados DCA'!$L$9:$L$564,'Dados DCA'!$C$9:$C$564,$C15,'Dados DCA'!$E$9:$E$564,$D15,'Dados DCA'!$F$9:$F$564,"despesa_funcao_"&$E15)) -> 37850464 | H15: =IF(OR(G15="",SUMIFS('Cálculos Municipais'!$T$9:$T$28,'Cálculos Municipais'!$C$9:$C$28,$C15,'Cálculos Municipais'!$D$9:$D$28,$D15)=0),"",G15*SUMIFS('Cálculos Municipais'!$T$9:$T$28,'Cálculos Municipais'!$C$9:$C$28,$C15,'Cálculos Municipais'!$D$9:$D$28,$D15)) -> 54274408 | I15: =IF(OR(G15="",SUMIFS('Dados DCA'!$L$9:$L$564,'Dados DCA'!$C$9:$C$564,$C15,'Dados DCA'!$E$9:$E$564,$D15,'Dados DCA'!$F$9:$F$564,"despesa_empenhada_exceto_intra")=0),"",G15/SUMIFS('Dados DCA'!$L$9:$L$564,'Dados DCA'!$C$9:$C$564,$C15,'Dados DCA'!$E$9:$E$564,$D15,'Dados DCA'!$F$9:$F$564,"despesa_empenhada_exceto_intra")) -> 0.28351061 | J15: siconfi_dca_arcoverde_2017.json
C16: Arcoverde/PE | D16: 2017 | E16: 13 | F16: Cultura | G16: =IF(COUNTIFS('Dados DCA'!$C$9:$C$564,$C16,'Dados DCA'!$E$9:$E$564,$D16,'Dados DCA'!$F$9:$F$564,"despesa_funcao_"&$E16)=0,"",SUMIFS('Dados DCA'!$L$9:$L$564,'Dados DCA'!$C$9:$C$564,$C16,'Dados DCA'!$E$9:$E$564,$D16,'Dados DCA'!$F$9:$F$564,"despesa_funcao_"&$E16)) -> 188353.36 | H16: =IF(OR(G16="",SUMIFS('Cálculos Municipais'!$T$9:$T$28,'Cálculos Municipais'!$C$9:$C$28,$C16,'Cálculos Municipais'!$D$9:$D$28,$D16)=0),"",G16*SUMIFS('Cálculos Municipais'!$T$9:$T$28,'Cálculos Municipais'!$C$9:$C$28,$C16,'Cálculos Municipais'!$D$9:$D$28,$D16)) -> 270083.01 | I16: =IF(OR(G16="",SUMIFS('Dados DCA'!$L$9:$L$564,'Dados DCA'!$C$9:$C$564,$C16,'Dados DCA'!$E$9:$E$564,$D16,'Dados DCA'!$F$9:$F$564,"despesa_empenhada_exceto_intra")=0),"",G16/SUMIFS('Dados DCA'!$L$9:$L$564,'Dados DCA'!$C$9:$C$564,$C16,'Dados DCA'!$E$9:$E$564,$D16,'Dados DCA'!$F$9:$F$564,"despesa_empenhada_exceto_intra")) -> 0.0014108196 | J16: siconfi_dca_arcoverde_2017.json
C17: Arcoverde/PE | D17: 2017 | E17: 15 | F17: Urbanismo | G17: =IF(COUNTIFS('Dados DCA'!$C$9:$C$564,$C17,'Dados DCA'!$E$9:$E$564,$D17,'Dados DCA'!$F$9:$F$564,"despesa_funcao_"&$E17)=0,"",SUMIFS('Dados DCA'!$L$9:$L$564,'Dados DCA'!$C$9:$C$564,$C17,'Dados DCA'!$E$9:$E$564,$D17,'Dados DCA'!$F$9:$F$564,"despesa_funcao_"&$E17)) -> 7540464.7 | H17: =IF(OR(G17="",SUMIFS('Cálculos Municipais'!$T$9:$T$28,'Cálculos Municipais'!$C$9:$C$28,$C17,'Cálculos Municipais'!$D$9:$D$28,$D17)=0),"",G17*SUMIFS('Cálculos Municipais'!$T$9:$T$28,'Cálculos Municipais'!$C$9:$C$28,$C17,'Cálculos Municipais'!$D$9:$D$28,$D17)) -> 10812397 | I17: =IF(OR(G17="",SUMIFS('Dados DCA'!$L$9:$L$564,'Dados DCA'!$C$9:$C$564,$C17,'Dados DCA'!$E$9:$E$564,$D17,'Dados DCA'!$F$9:$F$564,"despesa_empenhada_exceto_intra")=0),"",G17/SUMIFS('Dados DCA'!$L$9:$L$564,'Dados DCA'!$C$9:$C$564,$C17,'Dados DCA'!$E$9:$E$564,$D17,'Dados DCA'!$F$9:$F$564,"despesa_empenhada_exceto_intra")) -> 0.056480199 | J17: siconfi_dca_arcoverde_2017.json
C18: Arcoverde/PE | D18: 2017 | E18: 17 | F18: Saneamento | G18: =IF(COUNTIFS('Dados DCA'!$C$9:$C$564,$C18,'Dados DCA'!$E$9:$E$564,$D18,'Dados DCA'!$F$9:$F$564,"despesa_funcao_"&$E18)=0,"",SUMIFS('Dados DCA'!$L$9:$L$564,'Dados DCA'!$C$9:$C$564,$C18,'Dados DCA'!$E$9:$E$564,$D18,'Dados DCA'!$F$9:$F$564,"despesa_funcao_"&$E18)) -> 44598.04 | H18: =IF(OR(G18="",SUMIFS('Cálculos Municipais'!$T$9:$T$28,'Cálculos Municipais'!$C$9:$C$28,$C18,'Cálculos Municipais'!$D$9:$D$28,$D18)=0),"",G18*SUMIFS('Cálculos Municipais'!$T$9:$T$28,'Cálculos Municipais'!$C$9:$C$28,$C18,'Cálculos Municipais'!$D$9:$D$28,$D18)) -> 63949.869 | I18: =IF(OR(G18="",SUMIFS('Dados DCA'!$L$9:$L$564,'Dados DCA'!$C$9:$C$564,$C18,'Dados DCA'!$E$9:$E$564,$D18,'Dados DCA'!$F$9:$F$564,"despesa_empenhada_exceto_intra")=0),"",G18/SUMIFS('Dados DCA'!$L$9:$L$564,'Dados DCA'!$C$9:$C$564,$C18,'Dados DCA'!$E$9:$E$564,$D18,'Dados DCA'!$F$9:$F$564,"despesa_empenhada_exceto_intra")) -> 0.00033405185 | J18: siconfi_dca_arcoverde_2017.json
C19: Arcoverde/PE | D19: 2017 | E19: 18 | F19: Gestão Ambiental | G19: =IF(COUNTIFS('Dados DCA'!$C$9:$C$564,$C19,'Dados DCA'!$E$9:$E$564,$D19,'Dados DCA'!$F$9:$F$564,"despesa_funcao_"&$E19)=0,"",SUMIFS('Dados DCA'!$L$9:$L$564,'Dados DCA'!$C$9:$C$564,$C19,'Dados DCA'!$E$9:$E$564,$D19,'Dados DCA'!$F$9:$F$564,"despesa_funcao_"&$E19)) -> 1044012.1 | H19: =IF(OR(G19="",SUMIFS('Cálculos Municipais'!$T$9:$T$28,'Cálculos Municipais'!$C$9:$C$28,$C19,'Cálculos Municipais'!$D$9:$D$28,$D19)=0),"",G19*SUMIFS('Cálculos Municipais'!$T$9:$T$28,'Cálculos Municipais'!$C$9:$C$28,$C19,'Cálculos Municipais'!$D$9:$D$28,$D19)) -> 1497026.3 | I19: =IF(OR(G19="",SUMIFS('Dados DCA'!$L$9:$L$564,'Dados DCA'!$C$9:$C$564,$C19,'Dados DCA'!$E$9:$E$564,$D19,'Dados DCA'!$F$9:$F$564,"despesa_empenhada_exceto_intra")=0),"",G19/SUMIFS('Dados DCA'!$L$9:$L$564,'Dados DCA'!$C$9:$C$564,$C19,'Dados DCA'!$E$9:$E$564,$D19,'Dados DCA'!$F$9:$F$564,"despesa_empenhada_exceto_intra")) -> 0.0078199438 | J19: siconfi_dca_arcoverde_2017.json
C20: Arcoverde/PE | D20: 2017 | E20: 20 | F20: Agricultura | G20: =IF(COUNTIFS('Dados DCA'!$C$9:$C$564,$C20,'Dados DCA'!$E$9:$E$564,$D20,'Dados DCA'!$F$9:$F$564,"despesa_funcao_"&$E20)=0,"",SUMIFS('Dados DCA'!$L$9:$L$564,'Dados DCA'!$C$9:$C$564,$C20,'Dados DCA'!$E$9:$E$564,$D20,'Dados DCA'!$F$9:$F$564,"despesa_funcao_"&$E20)) -> 82563 | H20: =IF(OR(G20="",SUMIFS('Cálculos Municipais'!$T$9:$T$28,'Cálculos Municipais'!$C$9:$C$28,$C20,'Cálculos Municipais'!$D$9:$D$28,$D20)=0),"",G20*SUMIFS('Cálculos Municipais'!$T$9:$T$28,'Cálculos Municipais'!$C$9:$C$28,$C20,'Cálculos Municipais'!$D$9:$D$28,$D20)) -> 118388.46 | I20: =IF(OR(G20="",SUMIFS('Dados DCA'!$L$9:$L$564,'Dados DCA'!$C$9:$C$564,$C20,'Dados DCA'!$E$9:$E$564,$D20,'Dados DCA'!$F$9:$F$564,"despesa_empenhada_exceto_intra")=0),"",G20/SUMIFS('Dados DCA'!$L$9:$L$564,'Dados DCA'!$C$9:$C$564,$C20,'Dados DCA'!$E$9:$E$564,$D20,'Dados DCA'!$F$9:$F$564,"despesa_empenhada_exceto_intra")) -> 0.00061842006 | J20: siconfi_dca_arcoverde_2017.json
... C264: Araripina/PE | D264: 2024 | E264: 28 | F264: Encargos Especiais | G264: =IF(COUNTIFS('Dados DCA'!$C$9:$C$564,$C264,'Dados DCA'!$E$9:$E$564,$D264,'Dados DCA'!$F$9:$F$564,"despesa_funcao_"&$E264)=0,"",SUMIFS('Dados DCA'!$L$9:$L$564,'Dados DCA'!$C$9:$C$564,$C264,'Dados DCA'!$E$9:$E$564,$D264,'Dados DCA'!$F$9:$F$564,"despesa_funcao_"&$E264)) -> 10373776 | H264: =IF(OR(G264="",SUMIFS('Cálculos Municipais'!$T$9:$T$28,'Cálculos Municipais'!$C$9:$C$28,$C264,'Cálculos Municipais'!$D$9:$D$28,$D264)=0),"",G264*SUMIFS('Cálculos Municipais'!$T$9:$T$28,'Cálculos Municipais'!$C$9:$C$28,$C264,'Cálculos Municipais'!$D$9:$D$28,$D264)) -> 10373776 | I264: =IF(OR(G264="",SUMIFS('Dados DCA'!$L$9:$L$564,'Dados DCA'!$C$9:$C$564,$C264,'Dados DCA'!$E$9:$E$564,$D264,'Dados DCA'!$F$9:$F$564,"despesa_empenhada_exceto_intra")=0),"",G264/SUMIFS('Dados DCA'!$L$9:$L$564,'Dados DCA'!$C$9:$C$564,$C264,'Dados DCA'!$E$9:$E$564,$D264,'Dados DCA'!$F$9:$F$564,"despesa_empenhada_exceto_intra")) -> 0.028172295 | J264: siconfi_dca_araripina_2024.json

Sheet Fontes e Métodos
C3: Fontes e métodos
C5: Definições de medição, cobertura, transformação e limitações incorporadas à planilha.
C6: Consulte os arquivos JSON/CSV originais em data/brutos e os scripts em scripts/.
C8: Tópico | D8: Definição, critério ou fonte
C9: Siconfi/STN DCA | D9: Contas anuais municipais — consulta DCA por exercício e código IBGE; 20 respostas JSON em data/brutos. https://apidatalake.tesouro.gov.br/docs/siconfi/
C10: Receita | D10: Total bruto reportado; FUNDEB/outros descontos registrados em campos separados. Líquido após deduções reportadas não é necessariamente líquido completo quando outra dedução não aparece.
C11: Despesa | D11: Empenhada, liquidada e paga são estágios distintos; as séries não são misturadas. Valor total e valor exceto intra aparecem separadamente.
C12: Transferências | D12: Transferências correntes totais são uma rubrica ampla. Proxy intergovernamental mantém quebra de classificação: agregado antigo 2015–2017; contas de União + Estados de primeiro nível a partir de 2018.
C13: Tributação própria | D13: Receitas tributárias municipais brutas conforme código selecionado no DCA; proporção dividida por receita bruta total reportada.
C14: IBGE/SIDRA população | D14: Tabela 6579, variável 9324, estimativa de referência 1º de julho; 2022 substituída pelo Censo 2022, tabela 4709, variável 93. Faltam estimativas na série extraída em 2023.
C15: IBGE/SIDRA PIB | D15: Tabela 5938, variável 37, PIB municipal a preços correntes, unidade mil R$; multiplicar por 1.000 para R$. Cobertura 2015–2023; sem valor de 2024.
C16: IBGE/SIDRA IPCA | D16: Tabela 1737, variável 2266, número-índice mensal Brasil; fator t = média mensal de 2024 / média mensal do ano t; real de 2024 = nominal × fator.
C17: Eurostat | D17: gov_10dd_edpt1; Belgium (BE), annual, sector S13 General government, unit PC_GDP; B9 net lending/borrowing e GD consolidated gross debt. https://ec.europa.eu/eurostat/databrowser/product/view/gov_10dd_edpt1
C18: Ausências | D18: Valor ausente permanece vazio; não se converte ausência em zero. Série funcional está disponível de 2017 a 2024; 2015–2016 não aparecem nos quadros funcionais recuperados.
C19: Unidades institucionais | D19: Bélgica: governo geral nacional, ESA 2010; Brasil: municípios. PIB/percentuais são indicadores de escala, não equivalência de competências ou regime fiscal.
C20: Data da coleta | D20: 2026-10-25

Sheet Validação
C3: Validação automática
C5: Testes executados contra dados tratados e observações de cobertura.
C6: Ver scripts/validacao.py e data/tratados/relatorio_validacao.txt.
C8: Verificação | D8: Resultado
C9: Controle 1 | D9: VALIDAÇÃO DA BASE — PASS
C10: Controle 2 | D10: Observações municipais: 20; 10 anos × 2 municípios.
C11: Controle 3 | D11: Dados fiscais essenciais completos: 20/20.
C12: Controle 4 | D12: População disponível: 18/20; 2023 permanece ausente; 2022 usa Censo.
C13: Controle 5 | D13: PIB disponível: 18/20; 2024 permanece ausente.
C14: Controle 6 | D14: IPCA: 12 meses por ano em 2015–2024; sem imputação.
C15: Controle 7 | D15: Despesas totais e componentes intra/extra reconciliados dentro de R$ 0,02.
C16: Controle 8 | D16: Receitas intra/extra reconciliadas em 2019–2024 dentro de R$ 0,02.
C17: Controle 9 | D17: Conta-pai/filha: nenhuma dupla contagem dentro do indicador selecionado.
C18: Controle 10 | D18: Despesas funcionais: 256 linhas; 2017–2024; soma das funções de primeiro nível reconcilia com despesa empenhada exceto intra.
C19: Controle 11 | D19: Eurostat: 2015–2025; 2025 = déficit -5,2% e dívida bruta 108,1% do PIB.
C20: Controle 12 | D20: Deduções não exibidas na fonte permanecem em branco; o saldo derivado é rotulado como baseado nas deduções reportadas.
